{
  "Maharashtra": {
    "Ahmednagar": {
      "Ahmednagar": [
        "Ahmednagar",
        "Sangamner",
        "Shrirampur",
        "Kopargaon",
        "Rahuri",
        "Shirdi",
        "Akole",
        "Jamkhed",
        "Karjat",
        "Nevasa",
        "Parner",
        "Pathardi",
        "Rahata",
        "Shevgaon",
        "Shrigonda"
      ],
      "Akole": [
        "Akole",
        "Ahmednagar",
        "Sangamner",
        "Shrirampur",
        "Kopargaon",
        "Rahuri",
        "Shirdi",
        "Jamkhed",
        "Karjat",
        "Nevasa",
        "Parner",
        "Pathardi",
        "Rahata",
        "Shevgaon",
        "Shrigonda"
      ],
      "Jamkhed": [
        "Jamkhed",
        "Ahmednagar",
        "Sangamner",
        "Shrirampur",
        "Kopargaon",
        "Rahuri",
        "Shirdi",
        "Akole",
        "Karjat",
        "Nevasa",
        "Parner",
        "Pathardi",
        "Rahata",
        "Shevgaon",
        "Shrigonda"
      ],
      "Karjat": [
        "Karjat",
        "Ahmednagar",
        "Sangamner",
        "Shrirampur",
        "Kopargaon",
        "Rahuri",
        "Shirdi",
        "Akole",
        "Jamkhed",
        "Nevasa",
        "Parner",
        "Pathardi",
        "Rahata",
        "Shevgaon",
        "Shrigonda"
      ],
      "Kopargaon": [
        "Kopargaon",
        "Ahmednagar",
        "Sangamner",
        "Shrirampur",
        "Rahuri",
        "Shirdi",
        "Akole",
        "Jamkhed",
        "Karjat",
        "Nevasa",
        "Parner",
        "Pathardi",
        "Rahata",
        "Shevgaon",
        "Shrigonda"
      ],
      "Nevasa": [
        "Nevasa",
        "Ahmednagar",
        "Sangamner",
        "Shrirampur",
        "Kopargaon",
        "Rahuri",
        "Shirdi",
        "Akole",
        "Jamkhed",
        "Karjat",
        "Parner",
        "Pathardi",
        "Rahata",
        "Shevgaon",
        "Shrigonda"
      ],
      "Parner": [
        "Parner",
        "Ahmednagar",
        "Sangamner",
        "Shrirampur",
        "Kopargaon",
        "Rahuri",
        "Shirdi",
        "Akole",
        "Jamkhed",
        "Karjat",
        "Nevasa",
        "Pathardi",
        "Rahata",
        "Shevgaon",
        "Shrigonda"
      ],
      "Pathardi": [
        "Pathardi",
        "Ahmednagar",
        "Sangamner",
        "Shrirampur",
        "Kopargaon",
        "Rahuri",
        "Shirdi",
        "Akole",
        "Jamkhed",
        "Karjat",
        "Nevasa",
        "Parner",
        "Rahata",
        "Shevgaon",
        "Shrigonda"
      ],
      "Rahata": [
        "Rahata",
        "Ahmednagar",
        "Sangamner",
        "Shrirampur",
        "Kopargaon",
        "Rahuri",
        "Shirdi",
        "Akole",
        "Jamkhed",
        "Karjat",
        "Nevasa",
        "Parner",
        "Pathardi",
        "Shevgaon",
        "Shrigonda"
      ],
      "Rahuri": [
        "Rahuri",
        "Ahmednagar",
        "Sangamner",
        "Shrirampur",
        "Kopargaon",
        "Shirdi",
        "Akole",
        "Jamkhed",
        "Karjat",
        "Nevasa",
        "Parner",
        "Pathardi",
        "Rahata",
        "Shevgaon",
        "Shrigonda"
      ],
      "Sangamner": [
        "Sangamner",
        "Ahmednagar",
        "Shrirampur",
        "Kopargaon",
        "Rahuri",
        "Shirdi",
        "Akole",
        "Jamkhed",
        "Karjat",
        "Nevasa",
        "Parner",
        "Pathardi",
        "Rahata",
        "Shevgaon",
        "Shrigonda"
      ],
      "Shevgaon": [
        "Shevgaon",
        "Ahmednagar",
        "Sangamner",
        "Shrirampur",
        "Kopargaon",
        "Rahuri",
        "Shirdi",
        "Akole",
        "Jamkhed",
        "Karjat",
        "Nevasa",
        "Parner",
        "Pathardi",
        "Rahata",
        "Shrigonda"
      ],
      "Shrigonda": [
        "Shrigonda",
        "Ahmednagar",
        "Sangamner",
        "Shrirampur",
        "Kopargaon",
        "Rahuri",
        "Shirdi",
        "Akole",
        "Jamkhed",
        "Karjat",
        "Nevasa",
        "Parner",
        "Pathardi",
        "Rahata",
        "Shevgaon"
      ],
      "Shrirampur": [
        "Shrirampur",
        "Ahmednagar",
        "Sangamner",
        "Kopargaon",
        "Rahuri",
        "Shirdi",
        "Akole",
        "Jamkhed",
        "Karjat",
        "Nevasa",
        "Parner",
        "Pathardi",
        "Rahata",
        "Shevgaon",
        "Shrigonda"
      ]
    },
    "Akola": {
      "Akola": [
        "Akola",
        "Akot",
        "Murtijapur",
        "Balapur",
        "Barshitakli",
        "Patur",
        "Telhara"
      ],
      "Akot": [
        "Akot",
        "Akola",
        "Murtijapur",
        "Balapur",
        "Barshitakli",
        "Patur",
        "Telhara"
      ],
      "Balapur": [
        "Balapur",
        "Akola",
        "Akot",
        "Murtijapur",
        "Barshitakli",
        "Patur",
        "Telhara"
      ],
      "Barshitakli": [
        "Barshitakli",
        "Akola",
        "Akot",
        "Murtijapur",
        "Balapur",
        "Patur",
        "Telhara"
      ],
      "Murtijapur": [
        "Murtijapur",
        "Akola",
        "Akot",
        "Balapur",
        "Barshitakli",
        "Patur",
        "Telhara"
      ],
      "Patur": [
        "Patur",
        "Akola",
        "Akot",
        "Murtijapur",
        "Balapur",
        "Barshitakli",
        "Telhara"
      ],
      "Telhara": [
        "Telhara",
        "Akola",
        "Akot",
        "Murtijapur",
        "Balapur",
        "Barshitakli",
        "Patur"
      ]
    },
    "Amravati": {
      "Achalpur": [
        "Achalpur",
        "Amravati",
        "Warud",
        "Daryapur",
        "Morshi",
        "Anjangaon Surji",
        "Bhatkuli",
        "Chandur Bazar",
        "Chandur Railway",
        "Chikhaldara",
        "Dhamangaon Railway",
        "Dharni",
        "Nandgaon-Khandeshwar",
        "Teosa"
      ],
      "Amravati": [
        "Amravati",
        "Achalpur",
        "Warud",
        "Daryapur",
        "Morshi",
        "Anjangaon Surji",
        "Bhatkuli",
        "Chandur Bazar",
        "Chandur Railway",
        "Chikhaldara",
        "Dhamangaon Railway",
        "Dharni",
        "Nandgaon-Khandeshwar",
        "Teosa"
      ],
      "Anjangaon Surji": [
        "Anjangaon Surji",
        "Amravati",
        "Achalpur",
        "Warud",
        "Daryapur",
        "Morshi",
        "Bhatkuli",
        "Chandur Bazar",
        "Chandur Railway",
        "Chikhaldara",
        "Dhamangaon Railway",
        "Dharni",
        "Nandgaon-Khandeshwar",
        "Teosa"
      ],
      "Bhatkuli": [
        "Bhatkuli",
        "Amravati",
        "Achalpur",
        "Warud",
        "Daryapur",
        "Morshi",
        "Anjangaon Surji",
        "Chandur Bazar",
        "Chandur Railway",
        "Chikhaldara",
        "Dhamangaon Railway",
        "Dharni",
        "Nandgaon-Khandeshwar",
        "Teosa"
      ],
      "Chandur Bazar": [
        "Chandur Bazar",
        "Amravati",
        "Achalpur",
        "Warud",
        "Daryapur",
        "Morshi",
        "Anjangaon Surji",
        "Bhatkuli",
        "Chandur Railway",
        "Chikhaldara",
        "Dhamangaon Railway",
        "Dharni",
        "Nandgaon-Khandeshwar",
        "Teosa"
      ],
      "Chandur Railway": [
        "Chandur Railway",
        "Amravati",
        "Achalpur",
        "Warud",
        "Daryapur",
        "Morshi",
        "Anjangaon Surji",
        "Bhatkuli",
        "Chandur Bazar",
        "Chikhaldara",
        "Dhamangaon Railway",
        "Dharni",
        "Nandgaon-Khandeshwar",
        "Teosa"
      ],
      "Chikhaldara": [
        "Chikhaldara",
        "Amravati",
        "Achalpur",
        "Warud",
        "Daryapur",
        "Morshi",
        "Anjangaon Surji",
        "Bhatkuli",
        "Chandur Bazar",
        "Chandur Railway",
        "Dhamangaon Railway",
        "Dharni",
        "Nandgaon-Khandeshwar",
        "Teosa"
      ],
      "Daryapur": [
        "Daryapur",
        "Amravati",
        "Achalpur",
        "Warud",
        "Morshi",
        "Anjangaon Surji",
        "Bhatkuli",
        "Chandur Bazar",
        "Chandur Railway",
        "Chikhaldara",
        "Dhamangaon Railway",
        "Dharni",
        "Nandgaon-Khandeshwar",
        "Teosa"
      ],
      "Dhamangaon Railway": [
        "Dhamangaon Railway",
        "Amravati",
        "Achalpur",
        "Warud",
        "Daryapur",
        "Morshi",
        "Anjangaon Surji",
        "Bhatkuli",
        "Chandur Bazar",
        "Chandur Railway",
        "Chikhaldara",
        "Dharni",
        "Nandgaon-Khandeshwar",
        "Teosa"
      ],
      "Dharni": [
        "Dharni",
        "Amravati",
        "Achalpur",
        "Warud",
        "Daryapur",
        "Morshi",
        "Anjangaon Surji",
        "Bhatkuli",
        "Chandur Bazar",
        "Chandur Railway",
        "Chikhaldara",
        "Dhamangaon Railway",
        "Nandgaon-Khandeshwar",
        "Teosa"
      ],
      "Morshi": [
        "Morshi",
        "Amravati",
        "Achalpur",
        "Warud",
        "Daryapur",
        "Anjangaon Surji",
        "Bhatkuli",
        "Chandur Bazar",
        "Chandur Railway",
        "Chikhaldara",
        "Dhamangaon Railway",
        "Dharni",
        "Nandgaon-Khandeshwar",
        "Teosa"
      ],
      "Nandgaon-Khandeshwar": [
        "Nandgaon-Khandeshwar",
        "Amravati",
        "Achalpur",
        "Warud",
        "Daryapur",
        "Morshi",
        "Anjangaon Surji",
        "Bhatkuli",
        "Chandur Bazar",
        "Chandur Railway",
        "Chikhaldara",
        "Dhamangaon Railway",
        "Dharni",
        "Teosa"
      ],
      "Teosa": [
        "Teosa",
        "Amravati",
        "Achalpur",
        "Warud",
        "Daryapur",
        "Morshi",
        "Anjangaon Surji",
        "Bhatkuli",
        "Chandur Bazar",
        "Chandur Railway",
        "Chikhaldara",
        "Dhamangaon Railway",
        "Dharni",
        "Nandgaon-Khandeshwar"
      ],
      "Warud": [
        "Warud",
        "Amravati",
        "Achalpur",
        "Daryapur",
        "Morshi",
        "Anjangaon Surji",
        "Bhatkuli",
        "Chandur Bazar",
        "Chandur Railway",
        "Chikhaldara",
        "Dhamangaon Railway",
        "Dharni",
        "Nandgaon-Khandeshwar",
        "Teosa"
      ]
    },
    "Beed": {
      "Ambejogai": [
        "Ambejogai",
        "Beed",
        "Ambajogai",
        "Parli",
        "Majalgaon",
        "Georai",
        "Ashti",
        "Dharur",
        "Kaij",
        "Patoda",
        "Shirur Kasar",
        "Wadwani"
      ],
      "Ashti": [
        "Ashti",
        "Beed",
        "Ambajogai",
        "Parli",
        "Majalgaon",
        "Georai",
        "Dharur",
        "Kaij",
        "Patoda",
        "Shirur Kasar",
        "Wadwani",
        "Ambejogai"
      ],
      "Beed": [
        "Beed",
        "Ambajogai",
        "Parli",
        "Majalgaon",
        "Georai",
        "Ashti",
        "Dharur",
        "Kaij",
        "Patoda",
        "Shirur Kasar",
        "Wadwani",
        "Ambejogai"
      ],
      "Dharur": [
        "Dharur",
        "Beed",
        "Ambajogai",
        "Parli",
        "Majalgaon",
        "Georai",
        "Ashti",
        "Kaij",
        "Patoda",
        "Shirur Kasar",
        "Wadwani",
        "Ambejogai"
      ],
      "Georai": [
        "Georai",
        "Beed",
        "Ambajogai",
        "Parli",
        "Majalgaon",
        "Ashti",
        "Dharur",
        "Kaij",
        "Patoda",
        "Shirur Kasar",
        "Wadwani",
        "Ambejogai"
      ],
      "Kaij": [
        "Kaij",
        "Beed",
        "Ambajogai",
        "Parli",
        "Majalgaon",
        "Georai",
        "Ashti",
        "Dharur",
        "Patoda",
        "Shirur Kasar",
        "Wadwani",
        "Ambejogai"
      ],
      "Majalgaon": [
        "Majalgaon",
        "Beed",
        "Ambajogai",
        "Parli",
        "Georai",
        "Ashti",
        "Dharur",
        "Kaij",
        "Patoda",
        "Shirur Kasar",
        "Wadwani",
        "Ambejogai"
      ],
      "Parli": [
        "Parli",
        "Beed",
        "Ambajogai",
        "Majalgaon",
        "Georai",
        "Ashti",
        "Dharur",
        "Kaij",
        "Patoda",
        "Shirur Kasar",
        "Wadwani",
        "Ambejogai"
      ],
      "Patoda": [
        "Patoda",
        "Beed",
        "Ambajogai",
        "Parli",
        "Majalgaon",
        "Georai",
        "Ashti",
        "Dharur",
        "Kaij",
        "Shirur Kasar",
        "Wadwani",
        "Ambejogai"
      ],
      "Shirur Kasar": [
        "Shirur Kasar",
        "Beed",
        "Ambajogai",
        "Parli",
        "Majalgaon",
        "Georai",
        "Ashti",
        "Dharur",
        "Kaij",
        "Patoda",
        "Wadwani",
        "Ambejogai"
      ],
      "Wadwani": [
        "Wadwani",
        "Beed",
        "Ambajogai",
        "Parli",
        "Majalgaon",
        "Georai",
        "Ashti",
        "Dharur",
        "Kaij",
        "Patoda",
        "Shirur Kasar",
        "Ambejogai"
      ]
    },
    "Bhandara": {
      "Bhandara": [
        "Bhandara",
        "Tumsar",
        "Pauni",
        "Lakhandur",
        "Lakhani",
        "Mohadi",
        "Sakoli"
      ],
      "Lakhandur": [
        "Lakhandur",
        "Bhandara",
        "Tumsar",
        "Pauni",
        "Lakhani",
        "Mohadi",
        "Sakoli"
      ],
      "Lakhani": [
        "Lakhani",
        "Bhandara",
        "Tumsar",
        "Pauni",
        "Lakhandur",
        "Mohadi",
        "Sakoli"
      ],
      "Mohadi": [
        "Mohadi",
        "Bhandara",
        "Tumsar",
        "Pauni",
        "Lakhandur",
        "Lakhani",
        "Sakoli"
      ],
      "Pauni": [
        "Pauni",
        "Bhandara",
        "Tumsar",
        "Lakhandur",
        "Lakhani",
        "Mohadi",
        "Sakoli"
      ],
      "Sakoli": [
        "Sakoli",
        "Bhandara",
        "Tumsar",
        "Pauni",
        "Lakhandur",
        "Lakhani",
        "Mohadi"
      ],
      "Tumsar": [
        "Tumsar",
        "Bhandara",
        "Pauni",
        "Lakhandur",
        "Lakhani",
        "Mohadi",
        "Sakoli"
      ]
    },
    "Buldhana": {
      "Buldhana": [
        "Buldhana",
        "Khamgaon",
        "Malkapur",
        "Shegaon",
        "Chikhli",
        "Deulgaon Raja",
        "Jalgaon Jamod",
        "Lonar",
        "Mehkar",
        "Motala",
        "Nandura",
        "Sangrampur",
        "Sindkhed Raja"
      ],
      "Chikhli": [
        "Chikhli",
        "Buldhana",
        "Khamgaon",
        "Malkapur",
        "Shegaon",
        "Deulgaon Raja",
        "Jalgaon Jamod",
        "Lonar",
        "Mehkar",
        "Motala",
        "Nandura",
        "Sangrampur",
        "Sindkhed Raja"
      ],
      "Deulgaon Raja": [
        "Deulgaon Raja",
        "Buldhana",
        "Khamgaon",
        "Malkapur",
        "Shegaon",
        "Chikhli",
        "Jalgaon Jamod",
        "Lonar",
        "Mehkar",
        "Motala",
        "Nandura",
        "Sangrampur",
        "Sindkhed Raja"
      ],
      "Jalgaon Jamod": [
        "Jalgaon Jamod",
        "Buldhana",
        "Khamgaon",
        "Malkapur",
        "Shegaon",
        "Chikhli",
        "Deulgaon Raja",
        "Lonar",
        "Mehkar",
        "Motala",
        "Nandura",
        "Sangrampur",
        "Sindkhed Raja"
      ],
      "Khamgaon": [
        "Khamgaon",
        "Buldhana",
        "Malkapur",
        "Shegaon",
        "Chikhli",
        "Deulgaon Raja",
        "Jalgaon Jamod",
        "Lonar",
        "Mehkar",
        "Motala",
        "Nandura",
        "Sangrampur",
        "Sindkhed Raja"
      ],
      "Lonar": [
        "Lonar",
        "Buldhana",
        "Khamgaon",
        "Malkapur",
        "Shegaon",
        "Chikhli",
        "Deulgaon Raja",
        "Jalgaon Jamod",
        "Mehkar",
        "Motala",
        "Nandura",
        "Sangrampur",
        "Sindkhed Raja"
      ],
      "Malkapur": [
        "Malkapur",
        "Buldhana",
        "Khamgaon",
        "Shegaon",
        "Chikhli",
        "Deulgaon Raja",
        "Jalgaon Jamod",
        "Lonar",
        "Mehkar",
        "Motala",
        "Nandura",
        "Sangrampur",
        "Sindkhed Raja"
      ],
      "Mehkar": [
        "Mehkar",
        "Buldhana",
        "Khamgaon",
        "Malkapur",
        "Shegaon",
        "Chikhli",
        "Deulgaon Raja",
        "Jalgaon Jamod",
        "Lonar",
        "Motala",
        "Nandura",
        "Sangrampur",
        "Sindkhed Raja"
      ],
      "Motala": [
        "Motala",
        "Buldhana",
        "Khamgaon",
        "Malkapur",
        "Shegaon",
        "Chikhli",
        "Deulgaon Raja",
        "Jalgaon Jamod",
        "Lonar",
        "Mehkar",
        "Nandura",
        "Sangrampur",
        "Sindkhed Raja"
      ],
      "Nandura": [
        "Nandura",
        "Buldhana",
        "Khamgaon",
        "Malkapur",
        "Shegaon",
        "Chikhli",
        "Deulgaon Raja",
        "Jalgaon Jamod",
        "Lonar",
        "Mehkar",
        "Motala",
        "Sangrampur",
        "Sindkhed Raja"
      ],
      "Sangrampur": [
        "Sangrampur",
        "Buldhana",
        "Khamgaon",
        "Malkapur",
        "Shegaon",
        "Chikhli",
        "Deulgaon Raja",
        "Jalgaon Jamod",
        "Lonar",
        "Mehkar",
        "Motala",
        "Nandura",
        "Sindkhed Raja"
      ],
      "Shegaon": [
        "Shegaon",
        "Buldhana",
        "Khamgaon",
        "Malkapur",
        "Chikhli",
        "Deulgaon Raja",
        "Jalgaon Jamod",
        "Lonar",
        "Mehkar",
        "Motala",
        "Nandura",
        "Sangrampur",
        "Sindkhed Raja"
      ],
      "Sindkhed Raja": [
        "Sindkhed Raja",
        "Buldhana",
        "Khamgaon",
        "Malkapur",
        "Shegaon",
        "Chikhli",
        "Deulgaon Raja",
        "Jalgaon Jamod",
        "Lonar",
        "Mehkar",
        "Motala",
        "Nandura",
        "Sangrampur"
      ]
    },
    "Chandrapur": {
      "Ballarpur": [
        "Ballarpur",
        "Chandrapur",
        "Warora",
        "Brahmapuri",
        "Rajura",
        "Bhadravati",
        "Chimur",
        "Gondpipri",
        "Jiwati",
        "Korpana",
        "Mul",
        "Nagbhid",
        "Pombhurna",
        "Saoli",
        "Sindewahi"
      ],
      "Bhadravati": [
        "Bhadravati",
        "Chandrapur",
        "Ballarpur",
        "Warora",
        "Brahmapuri",
        "Rajura",
        "Chimur",
        "Gondpipri",
        "Jiwati",
        "Korpana",
        "Mul",
        "Nagbhid",
        "Pombhurna",
        "Saoli",
        "Sindewahi"
      ],
      "Brahmapuri": [
        "Brahmapuri",
        "Chandrapur",
        "Ballarpur",
        "Warora",
        "Rajura",
        "Bhadravati",
        "Chimur",
        "Gondpipri",
        "Jiwati",
        "Korpana",
        "Mul",
        "Nagbhid",
        "Pombhurna",
        "Saoli",
        "Sindewahi"
      ],
      "Chandrapur": [
        "Chandrapur",
        "Ballarpur",
        "Warora",
        "Brahmapuri",
        "Rajura",
        "Bhadravati",
        "Chimur",
        "Gondpipri",
        "Jiwati",
        "Korpana",
        "Mul",
        "Nagbhid",
        "Pombhurna",
        "Saoli",
        "Sindewahi"
      ],
      "Chimur": [
        "Chimur",
        "Chandrapur",
        "Ballarpur",
        "Warora",
        "Brahmapuri",
        "Rajura",
        "Bhadravati",
        "Gondpipri",
        "Jiwati",
        "Korpana",
        "Mul",
        "Nagbhid",
        "Pombhurna",
        "Saoli",
        "Sindewahi"
      ],
      "Gondpipri": [
        "Gondpipri",
        "Chandrapur",
        "Ballarpur",
        "Warora",
        "Brahmapuri",
        "Rajura",
        "Bhadravati",
        "Chimur",
        "Jiwati",
        "Korpana",
        "Mul",
        "Nagbhid",
        "Pombhurna",
        "Saoli",
        "Sindewahi"
      ],
      "Jiwati": [
        "Jiwati",
        "Chandrapur",
        "Ballarpur",
        "Warora",
        "Brahmapuri",
        "Rajura",
        "Bhadravati",
        "Chimur",
        "Gondpipri",
        "Korpana",
        "Mul",
        "Nagbhid",
        "Pombhurna",
        "Saoli",
        "Sindewahi"
      ],
      "Korpana": [
        "Korpana",
        "Chandrapur",
        "Ballarpur",
        "Warora",
        "Brahmapuri",
        "Rajura",
        "Bhadravati",
        "Chimur",
        "Gondpipri",
        "Jiwati",
        "Mul",
        "Nagbhid",
        "Pombhurna",
        "Saoli",
        "Sindewahi"
      ],
      "Mul": [
        "Mul",
        "Chandrapur",
        "Ballarpur",
        "Warora",
        "Brahmapuri",
        "Rajura",
        "Bhadravati",
        "Chimur",
        "Gondpipri",
        "Jiwati",
        "Korpana",
        "Nagbhid",
        "Pombhurna",
        "Saoli",
        "Sindewahi"
      ],
      "Nagbhid": [
        "Nagbhid",
        "Chandrapur",
        "Ballarpur",
        "Warora",
        "Brahmapuri",
        "Rajura",
        "Bhadravati",
        "Chimur",
        "Gondpipri",
        "Jiwati",
        "Korpana",
        "Mul",
        "Pombhurna",
        "Saoli",
        "Sindewahi"
      ],
      "Pombhurna": [
        "Pombhurna",
        "Chandrapur",
        "Ballarpur",
        "Warora",
        "Brahmapuri",
        "Rajura",
        "Bhadravati",
        "Chimur",
        "Gondpipri",
        "Jiwati",
        "Korpana",
        "Mul",
        "Nagbhid",
        "Saoli",
        "Sindewahi"
      ],
      "Rajura": [
        "Rajura",
        "Chandrapur",
        "Ballarpur",
        "Warora",
        "Brahmapuri",
        "Bhadravati",
        "Chimur",
        "Gondpipri",
        "Jiwati",
        "Korpana",
        "Mul",
        "Nagbhid",
        "Pombhurna",
        "Saoli",
        "Sindewahi"
      ],
      "Saoli": [
        "Saoli",
        "Chandrapur",
        "Ballarpur",
        "Warora",
        "Brahmapuri",
        "Rajura",
        "Bhadravati",
        "Chimur",
        "Gondpipri",
        "Jiwati",
        "Korpana",
        "Mul",
        "Nagbhid",
        "Pombhurna",
        "Sindewahi"
      ],
      "Sindewahi": [
        "Sindewahi",
        "Chandrapur",
        "Ballarpur",
        "Warora",
        "Brahmapuri",
        "Rajura",
        "Bhadravati",
        "Chimur",
        "Gondpipri",
        "Jiwati",
        "Korpana",
        "Mul",
        "Nagbhid",
        "Pombhurna",
        "Saoli"
      ],
      "Warora": [
        "Warora",
        "Chandrapur",
        "Ballarpur",
        "Brahmapuri",
        "Rajura",
        "Bhadravati",
        "Chimur",
        "Gondpipri",
        "Jiwati",
        "Korpana",
        "Mul",
        "Nagbhid",
        "Pombhurna",
        "Saoli",
        "Sindewahi"
      ]
    },
    "Chhatrapati Sambhajinagar": {
      "Chhatrapati Sambhajinagar": [
        "Chhatrapati Sambhajinagar",
        "Aurangabad",
        "Sillod",
        "Paithan",
        "Vaijapur",
        "Gangapur",
        "Kannad",
        "Khuldabad",
        "Phulambri",
        "Soegaon"
      ],
      "Gangapur": [
        "Gangapur",
        "Chhatrapati Sambhajinagar",
        "Aurangabad",
        "Sillod",
        "Paithan",
        "Vaijapur",
        "Kannad",
        "Khuldabad",
        "Phulambri",
        "Soegaon"
      ],
      "Kannad": [
        "Kannad",
        "Chhatrapati Sambhajinagar",
        "Aurangabad",
        "Sillod",
        "Paithan",
        "Vaijapur",
        "Gangapur",
        "Khuldabad",
        "Phulambri",
        "Soegaon"
      ],
      "Khuldabad": [
        "Khuldabad",
        "Chhatrapati Sambhajinagar",
        "Aurangabad",
        "Sillod",
        "Paithan",
        "Vaijapur",
        "Gangapur",
        "Kannad",
        "Phulambri",
        "Soegaon"
      ],
      "Paithan": [
        "Paithan",
        "Chhatrapati Sambhajinagar",
        "Aurangabad",
        "Sillod",
        "Vaijapur",
        "Gangapur",
        "Kannad",
        "Khuldabad",
        "Phulambri",
        "Soegaon"
      ],
      "Phulambri": [
        "Phulambri",
        "Chhatrapati Sambhajinagar",
        "Aurangabad",
        "Sillod",
        "Paithan",
        "Vaijapur",
        "Gangapur",
        "Kannad",
        "Khuldabad",
        "Soegaon"
      ],
      "Sillod": [
        "Sillod",
        "Chhatrapati Sambhajinagar",
        "Aurangabad",
        "Paithan",
        "Vaijapur",
        "Gangapur",
        "Kannad",
        "Khuldabad",
        "Phulambri",
        "Soegaon"
      ],
      "Soegaon": [
        "Soegaon",
        "Chhatrapati Sambhajinagar",
        "Aurangabad",
        "Sillod",
        "Paithan",
        "Vaijapur",
        "Gangapur",
        "Kannad",
        "Khuldabad",
        "Phulambri"
      ],
      "Vaijapur": [
        "Vaijapur",
        "Chhatrapati Sambhajinagar",
        "Aurangabad",
        "Sillod",
        "Paithan",
        "Gangapur",
        "Kannad",
        "Khuldabad",
        "Phulambri",
        "Soegaon"
      ]
    },
    "Dharashiv": {
      "Bhum": [
        "Bhum",
        "Dharashiv",
        "Osmanabad",
        "Tuljapur",
        "Omerga",
        "Kalamb",
        "Lohara",
        "Paranda",
        "Washi"
      ],
      "Dharashiv": [
        "Dharashiv",
        "Osmanabad",
        "Tuljapur",
        "Omerga",
        "Bhum",
        "Kalamb",
        "Lohara",
        "Paranda",
        "Washi"
      ],
      "Kalamb": [
        "Kalamb",
        "Dharashiv",
        "Osmanabad",
        "Tuljapur",
        "Omerga",
        "Bhum",
        "Lohara",
        "Paranda",
        "Washi"
      ],
      "Lohara": [
        "Lohara",
        "Dharashiv",
        "Osmanabad",
        "Tuljapur",
        "Omerga",
        "Bhum",
        "Kalamb",
        "Paranda",
        "Washi"
      ],
      "Omerga": [
        "Omerga",
        "Dharashiv",
        "Osmanabad",
        "Tuljapur",
        "Bhum",
        "Kalamb",
        "Lohara",
        "Paranda",
        "Washi"
      ],
      "Paranda": [
        "Paranda",
        "Dharashiv",
        "Osmanabad",
        "Tuljapur",
        "Omerga",
        "Bhum",
        "Kalamb",
        "Lohara",
        "Washi"
      ],
      "Tuljapur": [
        "Tuljapur",
        "Dharashiv",
        "Osmanabad",
        "Omerga",
        "Bhum",
        "Kalamb",
        "Lohara",
        "Paranda",
        "Washi"
      ],
      "Washi": [
        "Washi",
        "Dharashiv",
        "Osmanabad",
        "Tuljapur",
        "Omerga",
        "Bhum",
        "Kalamb",
        "Lohara",
        "Paranda"
      ]
    },
    "Dhule": {
      "Dhule": [
        "Dhule",
        "Shirpur",
        "Sakri",
        "Sindkheda"
      ],
      "Sakri": [
        "Sakri",
        "Dhule",
        "Shirpur",
        "Sindkheda"
      ],
      "Shirpur": [
        "Shirpur",
        "Dhule",
        "Sakri",
        "Sindkheda"
      ],
      "Sindkheda": [
        "Sindkheda",
        "Dhule",
        "Shirpur",
        "Sakri"
      ]
    },
    "Gadchiroli": {
      "Aheri": [
        "Aheri",
        "Gadchiroli",
        "Desaiganj",
        "Armori",
        "Bhamragad",
        "Chamorshi",
        "Dhanora",
        "Etapalli",
        "Korchi",
        "Kurkheda",
        "Mulchera",
        "Sironcha"
      ],
      "Armori": [
        "Armori",
        "Gadchiroli",
        "Desaiganj",
        "Aheri",
        "Bhamragad",
        "Chamorshi",
        "Dhanora",
        "Etapalli",
        "Korchi",
        "Kurkheda",
        "Mulchera",
        "Sironcha"
      ],
      "Bhamragad": [
        "Bhamragad",
        "Gadchiroli",
        "Desaiganj",
        "Aheri",
        "Armori",
        "Chamorshi",
        "Dhanora",
        "Etapalli",
        "Korchi",
        "Kurkheda",
        "Mulchera",
        "Sironcha"
      ],
      "Chamorshi": [
        "Chamorshi",
        "Gadchiroli",
        "Desaiganj",
        "Aheri",
        "Armori",
        "Bhamragad",
        "Dhanora",
        "Etapalli",
        "Korchi",
        "Kurkheda",
        "Mulchera",
        "Sironcha"
      ],
      "Desaiganj": [
        "Desaiganj",
        "Gadchiroli",
        "Aheri",
        "Armori",
        "Bhamragad",
        "Chamorshi",
        "Dhanora",
        "Etapalli",
        "Korchi",
        "Kurkheda",
        "Mulchera",
        "Sironcha"
      ],
      "Dhanora": [
        "Dhanora",
        "Gadchiroli",
        "Desaiganj",
        "Aheri",
        "Armori",
        "Bhamragad",
        "Chamorshi",
        "Etapalli",
        "Korchi",
        "Kurkheda",
        "Mulchera",
        "Sironcha"
      ],
      "Etapalli": [
        "Etapalli",
        "Gadchiroli",
        "Desaiganj",
        "Aheri",
        "Armori",
        "Bhamragad",
        "Chamorshi",
        "Dhanora",
        "Korchi",
        "Kurkheda",
        "Mulchera",
        "Sironcha"
      ],
      "Gadchiroli": [
        "Gadchiroli",
        "Desaiganj",
        "Aheri",
        "Armori",
        "Bhamragad",
        "Chamorshi",
        "Dhanora",
        "Etapalli",
        "Korchi",
        "Kurkheda",
        "Mulchera",
        "Sironcha"
      ],
      "Korchi": [
        "Korchi",
        "Gadchiroli",
        "Desaiganj",
        "Aheri",
        "Armori",
        "Bhamragad",
        "Chamorshi",
        "Dhanora",
        "Etapalli",
        "Kurkheda",
        "Mulchera",
        "Sironcha"
      ],
      "Kurkheda": [
        "Kurkheda",
        "Gadchiroli",
        "Desaiganj",
        "Aheri",
        "Armori",
        "Bhamragad",
        "Chamorshi",
        "Dhanora",
        "Etapalli",
        "Korchi",
        "Mulchera",
        "Sironcha"
      ],
      "Mulchera": [
        "Mulchera",
        "Gadchiroli",
        "Desaiganj",
        "Aheri",
        "Armori",
        "Bhamragad",
        "Chamorshi",
        "Dhanora",
        "Etapalli",
        "Korchi",
        "Kurkheda",
        "Sironcha"
      ],
      "Sironcha": [
        "Sironcha",
        "Gadchiroli",
        "Desaiganj",
        "Aheri",
        "Armori",
        "Bhamragad",
        "Chamorshi",
        "Dhanora",
        "Etapalli",
        "Korchi",
        "Kurkheda",
        "Mulchera"
      ]
    },
    "Gondia": {
      "Amgaon": [
        "Amgaon",
        "Gondia",
        "Tirora",
        "Arjuni Morgaon",
        "Deori",
        "Goregaon",
        "Sadak Arjuni",
        "Salekasa"
      ],
      "Arjuni Morgaon": [
        "Arjuni Morgaon",
        "Gondia",
        "Tirora",
        "Amgaon",
        "Deori",
        "Goregaon",
        "Sadak Arjuni",
        "Salekasa"
      ],
      "Deori": [
        "Deori",
        "Gondia",
        "Tirora",
        "Amgaon",
        "Arjuni Morgaon",
        "Goregaon",
        "Sadak Arjuni",
        "Salekasa"
      ],
      "Gondia": [
        "Gondia",
        "Tirora",
        "Amgaon",
        "Arjuni Morgaon",
        "Deori",
        "Goregaon",
        "Sadak Arjuni",
        "Salekasa"
      ],
      "Goregaon": [
        "Goregaon",
        "Gondia",
        "Tirora",
        "Amgaon",
        "Arjuni Morgaon",
        "Deori",
        "Sadak Arjuni",
        "Salekasa"
      ],
      "Sadak Arjuni": [
        "Sadak Arjuni",
        "Gondia",
        "Tirora",
        "Amgaon",
        "Arjuni Morgaon",
        "Deori",
        "Goregaon",
        "Salekasa"
      ],
      "Salekasa": [
        "Salekasa",
        "Gondia",
        "Tirora",
        "Amgaon",
        "Arjuni Morgaon",
        "Deori",
        "Goregaon",
        "Sadak Arjuni"
      ],
      "Tirora": [
        "Tirora",
        "Gondia",
        "Amgaon",
        "Arjuni Morgaon",
        "Deori",
        "Goregaon",
        "Sadak Arjuni",
        "Salekasa"
      ]
    },
    "Hingoli": {
      "Aundha Nagnath": [
        "Aundha Nagnath",
        "Hingoli",
        "Basmath",
        "Kalamnuri",
        "Sengaon"
      ],
      "Basmath": [
        "Basmath",
        "Hingoli",
        "Aundha Nagnath",
        "Kalamnuri",
        "Sengaon"
      ],
      "Hingoli": [
        "Hingoli",
        "Basmath",
        "Aundha Nagnath",
        "Kalamnuri",
        "Sengaon"
      ],
      "Kalamnuri": [
        "Kalamnuri",
        "Hingoli",
        "Basmath",
        "Aundha Nagnath",
        "Sengaon"
      ],
      "Sengaon": [
        "Sengaon",
        "Hingoli",
        "Basmath",
        "Aundha Nagnath",
        "Kalamnuri"
      ]
    },
    "Jalgaon": {
      "Amalner": [
        "Amalner",
        "Jalgaon",
        "Bhusawal",
        "Chalisgaon",
        "Pachora",
        "Raver",
        "Bhadgaon",
        "Bodwad",
        "Chopda",
        "Dharangaon",
        "Erandol",
        "Jamner",
        "Muktainagar",
        "Parola",
        "Yawal"
      ],
      "Bhadgaon": [
        "Bhadgaon",
        "Jalgaon",
        "Bhusawal",
        "Amalner",
        "Chalisgaon",
        "Pachora",
        "Raver",
        "Bodwad",
        "Chopda",
        "Dharangaon",
        "Erandol",
        "Jamner",
        "Muktainagar",
        "Parola",
        "Yawal"
      ],
      "Bhusawal": [
        "Bhusawal",
        "Jalgaon",
        "Amalner",
        "Chalisgaon",
        "Pachora",
        "Raver",
        "Bhadgaon",
        "Bodwad",
        "Chopda",
        "Dharangaon",
        "Erandol",
        "Jamner",
        "Muktainagar",
        "Parola",
        "Yawal"
      ],
      "Bodwad": [
        "Bodwad",
        "Jalgaon",
        "Bhusawal",
        "Amalner",
        "Chalisgaon",
        "Pachora",
        "Raver",
        "Bhadgaon",
        "Chopda",
        "Dharangaon",
        "Erandol",
        "Jamner",
        "Muktainagar",
        "Parola",
        "Yawal"
      ],
      "Chalisgaon": [
        "Chalisgaon",
        "Jalgaon",
        "Bhusawal",
        "Amalner",
        "Pachora",
        "Raver",
        "Bhadgaon",
        "Bodwad",
        "Chopda",
        "Dharangaon",
        "Erandol",
        "Jamner",
        "Muktainagar",
        "Parola",
        "Yawal"
      ],
      "Chopda": [
        "Chopda",
        "Jalgaon",
        "Bhusawal",
        "Amalner",
        "Chalisgaon",
        "Pachora",
        "Raver",
        "Bhadgaon",
        "Bodwad",
        "Dharangaon",
        "Erandol",
        "Jamner",
        "Muktainagar",
        "Parola",
        "Yawal"
      ],
      "Dharangaon": [
        "Dharangaon",
        "Jalgaon",
        "Bhusawal",
        "Amalner",
        "Chalisgaon",
        "Pachora",
        "Raver",
        "Bhadgaon",
        "Bodwad",
        "Chopda",
        "Erandol",
        "Jamner",
        "Muktainagar",
        "Parola",
        "Yawal"
      ],
      "Erandol": [
        "Erandol",
        "Jalgaon",
        "Bhusawal",
        "Amalner",
        "Chalisgaon",
        "Pachora",
        "Raver",
        "Bhadgaon",
        "Bodwad",
        "Chopda",
        "Dharangaon",
        "Jamner",
        "Muktainagar",
        "Parola",
        "Yawal"
      ],
      "Jalgaon": [
        "Jalgaon",
        "Bhusawal",
        "Amalner",
        "Chalisgaon",
        "Pachora",
        "Raver",
        "Bhadgaon",
        "Bodwad",
        "Chopda",
        "Dharangaon",
        "Erandol",
        "Jamner",
        "Muktainagar",
        "Parola",
        "Yawal"
      ],
      "Jamner": [
        "Jamner",
        "Jalgaon",
        "Bhusawal",
        "Amalner",
        "Chalisgaon",
        "Pachora",
        "Raver",
        "Bhadgaon",
        "Bodwad",
        "Chopda",
        "Dharangaon",
        "Erandol",
        "Muktainagar",
        "Parola",
        "Yawal"
      ],
      "Muktainagar": [
        "Muktainagar",
        "Jalgaon",
        "Bhusawal",
        "Amalner",
        "Chalisgaon",
        "Pachora",
        "Raver",
        "Bhadgaon",
        "Bodwad",
        "Chopda",
        "Dharangaon",
        "Erandol",
        "Jamner",
        "Parola",
        "Yawal"
      ],
      "Pachora": [
        "Pachora",
        "Jalgaon",
        "Bhusawal",
        "Amalner",
        "Chalisgaon",
        "Raver",
        "Bhadgaon",
        "Bodwad",
        "Chopda",
        "Dharangaon",
        "Erandol",
        "Jamner",
        "Muktainagar",
        "Parola",
        "Yawal"
      ],
      "Parola": [
        "Parola",
        "Jalgaon",
        "Bhusawal",
        "Amalner",
        "Chalisgaon",
        "Pachora",
        "Raver",
        "Bhadgaon",
        "Bodwad",
        "Chopda",
        "Dharangaon",
        "Erandol",
        "Jamner",
        "Muktainagar",
        "Yawal"
      ],
      "Raver": [
        "Raver",
        "Jalgaon",
        "Bhusawal",
        "Amalner",
        "Chalisgaon",
        "Pachora",
        "Bhadgaon",
        "Bodwad",
        "Chopda",
        "Dharangaon",
        "Erandol",
        "Jamner",
        "Muktainagar",
        "Parola",
        "Yawal"
      ],
      "Yawal": [
        "Yawal",
        "Jalgaon",
        "Bhusawal",
        "Amalner",
        "Chalisgaon",
        "Pachora",
        "Raver",
        "Bhadgaon",
        "Bodwad",
        "Chopda",
        "Dharangaon",
        "Erandol",
        "Jamner",
        "Muktainagar",
        "Parola"
      ]
    },
    "Jalna": {
      "Ambad": [
        "Ambad",
        "Jalna",
        "Partur",
        "Badnapur",
        "Bhokardan",
        "Ghansawangi",
        "Jafrabad",
        "Mantha"
      ],
      "Badnapur": [
        "Badnapur",
        "Jalna",
        "Ambad",
        "Partur",
        "Bhokardan",
        "Ghansawangi",
        "Jafrabad",
        "Mantha"
      ],
      "Bhokardan": [
        "Bhokardan",
        "Jalna",
        "Ambad",
        "Partur",
        "Badnapur",
        "Ghansawangi",
        "Jafrabad",
        "Mantha"
      ],
      "Ghansawangi": [
        "Ghansawangi",
        "Jalna",
        "Ambad",
        "Partur",
        "Badnapur",
        "Bhokardan",
        "Jafrabad",
        "Mantha"
      ],
      "Jafrabad": [
        "Jafrabad",
        "Jalna",
        "Ambad",
        "Partur",
        "Badnapur",
        "Bhokardan",
        "Ghansawangi",
        "Mantha"
      ],
      "Jalna": [
        "Jalna",
        "Ambad",
        "Partur",
        "Badnapur",
        "Bhokardan",
        "Ghansawangi",
        "Jafrabad",
        "Mantha"
      ],
      "Mantha": [
        "Mantha",
        "Jalna",
        "Ambad",
        "Partur",
        "Badnapur",
        "Bhokardan",
        "Ghansawangi",
        "Jafrabad"
      ],
      "Partur": [
        "Partur",
        "Jalna",
        "Ambad",
        "Badnapur",
        "Bhokardan",
        "Ghansawangi",
        "Jafrabad",
        "Mantha"
      ]
    },
    "Kolhapur": {
      "Ajra": [
        "Ajra",
        "Kolhapur",
        "Ichalkaranji",
        "Gadhinglaj",
        "Jaysingpur",
        "Kagal",
        "Bavda",
        "Bhudargad",
        "Chandgad",
        "Gaganbawada",
        "Hatkanangale",
        "Karvir",
        "Panhala",
        "Radhanagari",
        "Shahuwadi",
        "Shirol"
      ],
      "Bavda": [
        "Bavda",
        "Kolhapur",
        "Ichalkaranji",
        "Gadhinglaj",
        "Jaysingpur",
        "Kagal",
        "Ajra",
        "Bhudargad",
        "Chandgad",
        "Gaganbawada",
        "Hatkanangale",
        "Karvir",
        "Panhala",
        "Radhanagari",
        "Shahuwadi",
        "Shirol"
      ],
      "Bhudargad": [
        "Bhudargad",
        "Kolhapur",
        "Ichalkaranji",
        "Gadhinglaj",
        "Jaysingpur",
        "Kagal",
        "Ajra",
        "Bavda",
        "Chandgad",
        "Gaganbawada",
        "Hatkanangale",
        "Karvir",
        "Panhala",
        "Radhanagari",
        "Shahuwadi",
        "Shirol"
      ],
      "Chandgad": [
        "Chandgad",
        "Kolhapur",
        "Ichalkaranji",
        "Gadhinglaj",
        "Jaysingpur",
        "Kagal",
        "Ajra",
        "Bavda",
        "Bhudargad",
        "Gaganbawada",
        "Hatkanangale",
        "Karvir",
        "Panhala",
        "Radhanagari",
        "Shahuwadi",
        "Shirol"
      ],
      "Gadhinglaj": [
        "Gadhinglaj",
        "Kolhapur",
        "Ichalkaranji",
        "Jaysingpur",
        "Kagal",
        "Ajra",
        "Bavda",
        "Bhudargad",
        "Chandgad",
        "Gaganbawada",
        "Hatkanangale",
        "Karvir",
        "Panhala",
        "Radhanagari",
        "Shahuwadi",
        "Shirol"
      ],
      "Gaganbawada": [
        "Gaganbawada",
        "Kolhapur",
        "Ichalkaranji",
        "Gadhinglaj",
        "Jaysingpur",
        "Kagal",
        "Ajra",
        "Bavda",
        "Bhudargad",
        "Chandgad",
        "Hatkanangale",
        "Karvir",
        "Panhala",
        "Radhanagari",
        "Shahuwadi",
        "Shirol"
      ],
      "Hatkanangale": [
        "Hatkanangale",
        "Kolhapur",
        "Ichalkaranji",
        "Gadhinglaj",
        "Jaysingpur",
        "Kagal",
        "Ajra",
        "Bavda",
        "Bhudargad",
        "Chandgad",
        "Gaganbawada",
        "Karvir",
        "Panhala",
        "Radhanagari",
        "Shahuwadi",
        "Shirol"
      ],
      "Kagal": [
        "Kagal",
        "Kolhapur",
        "Ichalkaranji",
        "Gadhinglaj",
        "Jaysingpur",
        "Ajra",
        "Bavda",
        "Bhudargad",
        "Chandgad",
        "Gaganbawada",
        "Hatkanangale",
        "Karvir",
        "Panhala",
        "Radhanagari",
        "Shahuwadi",
        "Shirol"
      ],
      "Karvir": [
        "Karvir",
        "Kolhapur",
        "Ichalkaranji",
        "Gadhinglaj",
        "Jaysingpur",
        "Kagal",
        "Ajra",
        "Bavda",
        "Bhudargad",
        "Chandgad",
        "Gaganbawada",
        "Hatkanangale",
        "Panhala",
        "Radhanagari",
        "Shahuwadi",
        "Shirol"
      ],
      "Panhala": [
        "Panhala",
        "Kolhapur",
        "Ichalkaranji",
        "Gadhinglaj",
        "Jaysingpur",
        "Kagal",
        "Ajra",
        "Bavda",
        "Bhudargad",
        "Chandgad",
        "Gaganbawada",
        "Hatkanangale",
        "Karvir",
        "Radhanagari",
        "Shahuwadi",
        "Shirol"
      ],
      "Radhanagari": [
        "Radhanagari",
        "Kolhapur",
        "Ichalkaranji",
        "Gadhinglaj",
        "Jaysingpur",
        "Kagal",
        "Ajra",
        "Bavda",
        "Bhudargad",
        "Chandgad",
        "Gaganbawada",
        "Hatkanangale",
        "Karvir",
        "Panhala",
        "Shahuwadi",
        "Shirol"
      ],
      "Shahuwadi": [
        "Shahuwadi",
        "Kolhapur",
        "Ichalkaranji",
        "Gadhinglaj",
        "Jaysingpur",
        "Kagal",
        "Ajra",
        "Bavda",
        "Bhudargad",
        "Chandgad",
        "Gaganbawada",
        "Hatkanangale",
        "Karvir",
        "Panhala",
        "Radhanagari",
        "Shirol"
      ],
      "Shirol": [
        "Shirol",
        "Kolhapur",
        "Ichalkaranji",
        "Gadhinglaj",
        "Jaysingpur",
        "Kagal",
        "Ajra",
        "Bavda",
        "Bhudargad",
        "Chandgad",
        "Gaganbawada",
        "Hatkanangale",
        "Karvir",
        "Panhala",
        "Radhanagari",
        "Shahuwadi"
      ]
    },
    "Latur": {
      "Ahmadpur": [
        "Ahmadpur",
        "Latur",
        "Udgir",
        "Nilanga",
        "Ausa",
        "Chakur",
        "Deoni",
        "Jalkot",
        "Renapur",
        "Shirur Anantpal"
      ],
      "Ausa": [
        "Ausa",
        "Latur",
        "Udgir",
        "Nilanga",
        "Ahmadpur",
        "Chakur",
        "Deoni",
        "Jalkot",
        "Renapur",
        "Shirur Anantpal"
      ],
      "Chakur": [
        "Chakur",
        "Latur",
        "Udgir",
        "Nilanga",
        "Ausa",
        "Ahmadpur",
        "Deoni",
        "Jalkot",
        "Renapur",
        "Shirur Anantpal"
      ],
      "Deoni": [
        "Deoni",
        "Latur",
        "Udgir",
        "Nilanga",
        "Ausa",
        "Ahmadpur",
        "Chakur",
        "Jalkot",
        "Renapur",
        "Shirur Anantpal"
      ],
      "Jalkot": [
        "Jalkot",
        "Latur",
        "Udgir",
        "Nilanga",
        "Ausa",
        "Ahmadpur",
        "Chakur",
        "Deoni",
        "Renapur",
        "Shirur Anantpal"
      ],
      "Latur": [
        "Latur",
        "Udgir",
        "Nilanga",
        "Ausa",
        "Ahmadpur",
        "Chakur",
        "Deoni",
        "Jalkot",
        "Renapur",
        "Shirur Anantpal"
      ],
      "Nilanga": [
        "Nilanga",
        "Latur",
        "Udgir",
        "Ausa",
        "Ahmadpur",
        "Chakur",
        "Deoni",
        "Jalkot",
        "Renapur",
        "Shirur Anantpal"
      ],
      "Renapur": [
        "Renapur",
        "Latur",
        "Udgir",
        "Nilanga",
        "Ausa",
        "Ahmadpur",
        "Chakur",
        "Deoni",
        "Jalkot",
        "Shirur Anantpal"
      ],
      "Shirur Anantpal": [
        "Shirur Anantpal",
        "Latur",
        "Udgir",
        "Nilanga",
        "Ausa",
        "Ahmadpur",
        "Chakur",
        "Deoni",
        "Jalkot",
        "Renapur"
      ],
      "Udgir": [
        "Udgir",
        "Latur",
        "Nilanga",
        "Ausa",
        "Ahmadpur",
        "Chakur",
        "Deoni",
        "Jalkot",
        "Renapur",
        "Shirur Anantpal"
      ]
    },
    "Mumbai City": {
      "Mumbai City": [
        "Mumbai City",
        "Mumbai",
        "South Mumbai",
        "Byculla",
        "Colaba",
        "Dadar",
        "Fort",
        "Girgaon",
        "Malabar Hill",
        "Marine Lines",
        "Parel",
        "Worli"
      ]
    },
    "Mumbai Suburban": {
      "Andheri": [
        "Andheri",
        "Bandra",
        "Borivali",
        "Kurla",
        "Goregaon",
        "Malad",
        "Bhandup",
        "Chembur",
        "Ghatkopar",
        "Jogeshwari",
        "Kandivali",
        "Mulund",
        "Powai",
        "Santacruz",
        "Vikhroli",
        "Vile Parle"
      ],
      "Borivali": [
        "Borivali",
        "Andheri",
        "Bandra",
        "Kurla",
        "Goregaon",
        "Malad",
        "Bhandup",
        "Chembur",
        "Ghatkopar",
        "Jogeshwari",
        "Kandivali",
        "Mulund",
        "Powai",
        "Santacruz",
        "Vikhroli",
        "Vile Parle"
      ],
      "Kurla": [
        "Kurla",
        "Andheri",
        "Bandra",
        "Borivali",
        "Goregaon",
        "Malad",
        "Bhandup",
        "Chembur",
        "Ghatkopar",
        "Jogeshwari",
        "Kandivali",
        "Mulund",
        "Powai",
        "Santacruz",
        "Vikhroli",
        "Vile Parle"
      ]
    },
    "Nagpur": {
      "Bhiwapur": [
        "Bhiwapur",
        "Nagpur",
        "Kamptee",
        "Umred",
        "Katol",
        "Ramtek",
        "Hingna",
        "Kalameshwar",
        "Kuhi",
        "Mauda",
        "Narkhed",
        "Parseoni",
        "Savner",
        "Nagpur Rural",
        "Nagpur Urban"
      ],
      "Hingna": [
        "Hingna",
        "Nagpur",
        "Kamptee",
        "Umred",
        "Katol",
        "Ramtek",
        "Bhiwapur",
        "Kalameshwar",
        "Kuhi",
        "Mauda",
        "Narkhed",
        "Parseoni",
        "Savner",
        "Nagpur Rural",
        "Nagpur Urban"
      ],
      "Kalameshwar": [
        "Kalameshwar",
        "Nagpur",
        "Kamptee",
        "Umred",
        "Katol",
        "Ramtek",
        "Bhiwapur",
        "Hingna",
        "Kuhi",
        "Mauda",
        "Narkhed",
        "Parseoni",
        "Savner",
        "Nagpur Rural",
        "Nagpur Urban"
      ],
      "Kamptee": [
        "Kamptee",
        "Nagpur",
        "Umred",
        "Katol",
        "Ramtek",
        "Bhiwapur",
        "Hingna",
        "Kalameshwar",
        "Kuhi",
        "Mauda",
        "Narkhed",
        "Parseoni",
        "Savner",
        "Nagpur Rural",
        "Nagpur Urban"
      ],
      "Katol": [
        "Katol",
        "Nagpur",
        "Kamptee",
        "Umred",
        "Ramtek",
        "Bhiwapur",
        "Hingna",
        "Kalameshwar",
        "Kuhi",
        "Mauda",
        "Narkhed",
        "Parseoni",
        "Savner",
        "Nagpur Rural",
        "Nagpur Urban"
      ],
      "Kuhi": [
        "Kuhi",
        "Nagpur",
        "Kamptee",
        "Umred",
        "Katol",
        "Ramtek",
        "Bhiwapur",
        "Hingna",
        "Kalameshwar",
        "Mauda",
        "Narkhed",
        "Parseoni",
        "Savner",
        "Nagpur Rural",
        "Nagpur Urban"
      ],
      "Mauda": [
        "Mauda",
        "Nagpur",
        "Kamptee",
        "Umred",
        "Katol",
        "Ramtek",
        "Bhiwapur",
        "Hingna",
        "Kalameshwar",
        "Kuhi",
        "Narkhed",
        "Parseoni",
        "Savner",
        "Nagpur Rural",
        "Nagpur Urban"
      ],
      "Nagpur Rural": [
        "Nagpur Rural",
        "Nagpur",
        "Kamptee",
        "Umred",
        "Katol",
        "Ramtek",
        "Bhiwapur",
        "Hingna",
        "Kalameshwar",
        "Kuhi",
        "Mauda",
        "Narkhed",
        "Parseoni",
        "Savner",
        "Nagpur Urban"
      ],
      "Nagpur Urban": [
        "Nagpur Urban",
        "Nagpur",
        "Kamptee",
        "Umred",
        "Katol",
        "Ramtek",
        "Bhiwapur",
        "Hingna",
        "Kalameshwar",
        "Kuhi",
        "Mauda",
        "Narkhed",
        "Parseoni",
        "Savner",
        "Nagpur Rural"
      ],
      "Narkhed": [
        "Narkhed",
        "Nagpur",
        "Kamptee",
        "Umred",
        "Katol",
        "Ramtek",
        "Bhiwapur",
        "Hingna",
        "Kalameshwar",
        "Kuhi",
        "Mauda",
        "Parseoni",
        "Savner",
        "Nagpur Rural",
        "Nagpur Urban"
      ],
      "Parseoni": [
        "Parseoni",
        "Nagpur",
        "Kamptee",
        "Umred",
        "Katol",
        "Ramtek",
        "Bhiwapur",
        "Hingna",
        "Kalameshwar",
        "Kuhi",
        "Mauda",
        "Narkhed",
        "Savner",
        "Nagpur Rural",
        "Nagpur Urban"
      ],
      "Ramtek": [
        "Ramtek",
        "Nagpur",
        "Kamptee",
        "Umred",
        "Katol",
        "Bhiwapur",
        "Hingna",
        "Kalameshwar",
        "Kuhi",
        "Mauda",
        "Narkhed",
        "Parseoni",
        "Savner",
        "Nagpur Rural",
        "Nagpur Urban"
      ],
      "Savner": [
        "Savner",
        "Nagpur",
        "Kamptee",
        "Umred",
        "Katol",
        "Ramtek",
        "Bhiwapur",
        "Hingna",
        "Kalameshwar",
        "Kuhi",
        "Mauda",
        "Narkhed",
        "Parseoni",
        "Nagpur Rural",
        "Nagpur Urban"
      ],
      "Umred": [
        "Umred",
        "Nagpur",
        "Kamptee",
        "Katol",
        "Ramtek",
        "Bhiwapur",
        "Hingna",
        "Kalameshwar",
        "Kuhi",
        "Mauda",
        "Narkhed",
        "Parseoni",
        "Savner",
        "Nagpur Rural",
        "Nagpur Urban"
      ]
    },
    "Nanded": {
      "Ardhapur": [
        "Ardhapur",
        "Nanded",
        "Deglur",
        "Kinwat",
        "Mukhed",
        "Bhokar",
        "Biloli",
        "Dharmabad",
        "Hadgaon",
        "Himayatnagar",
        "Kandhar",
        "Loha",
        "Mahur",
        "Mudkhed",
        "Naigaon",
        "Umri"
      ],
      "Bhokar": [
        "Bhokar",
        "Nanded",
        "Deglur",
        "Kinwat",
        "Mukhed",
        "Ardhapur",
        "Biloli",
        "Dharmabad",
        "Hadgaon",
        "Himayatnagar",
        "Kandhar",
        "Loha",
        "Mahur",
        "Mudkhed",
        "Naigaon",
        "Umri"
      ],
      "Biloli": [
        "Biloli",
        "Nanded",
        "Deglur",
        "Kinwat",
        "Mukhed",
        "Ardhapur",
        "Bhokar",
        "Dharmabad",
        "Hadgaon",
        "Himayatnagar",
        "Kandhar",
        "Loha",
        "Mahur",
        "Mudkhed",
        "Naigaon",
        "Umri"
      ],
      "Deglur": [
        "Deglur",
        "Nanded",
        "Kinwat",
        "Mukhed",
        "Ardhapur",
        "Bhokar",
        "Biloli",
        "Dharmabad",
        "Hadgaon",
        "Himayatnagar",
        "Kandhar",
        "Loha",
        "Mahur",
        "Mudkhed",
        "Naigaon",
        "Umri"
      ],
      "Dharmabad": [
        "Dharmabad",
        "Nanded",
        "Deglur",
        "Kinwat",
        "Mukhed",
        "Ardhapur",
        "Bhokar",
        "Biloli",
        "Hadgaon",
        "Himayatnagar",
        "Kandhar",
        "Loha",
        "Mahur",
        "Mudkhed",
        "Naigaon",
        "Umri"
      ],
      "Hadgaon": [
        "Hadgaon",
        "Nanded",
        "Deglur",
        "Kinwat",
        "Mukhed",
        "Ardhapur",
        "Bhokar",
        "Biloli",
        "Dharmabad",
        "Himayatnagar",
        "Kandhar",
        "Loha",
        "Mahur",
        "Mudkhed",
        "Naigaon",
        "Umri"
      ],
      "Himayatnagar": [
        "Himayatnagar",
        "Nanded",
        "Deglur",
        "Kinwat",
        "Mukhed",
        "Ardhapur",
        "Bhokar",
        "Biloli",
        "Dharmabad",
        "Hadgaon",
        "Kandhar",
        "Loha",
        "Mahur",
        "Mudkhed",
        "Naigaon",
        "Umri"
      ],
      "Kandhar": [
        "Kandhar",
        "Nanded",
        "Deglur",
        "Kinwat",
        "Mukhed",
        "Ardhapur",
        "Bhokar",
        "Biloli",
        "Dharmabad",
        "Hadgaon",
        "Himayatnagar",
        "Loha",
        "Mahur",
        "Mudkhed",
        "Naigaon",
        "Umri"
      ],
      "Kinwat": [
        "Kinwat",
        "Nanded",
        "Deglur",
        "Mukhed",
        "Ardhapur",
        "Bhokar",
        "Biloli",
        "Dharmabad",
        "Hadgaon",
        "Himayatnagar",
        "Kandhar",
        "Loha",
        "Mahur",
        "Mudkhed",
        "Naigaon",
        "Umri"
      ],
      "Loha": [
        "Loha",
        "Nanded",
        "Deglur",
        "Kinwat",
        "Mukhed",
        "Ardhapur",
        "Bhokar",
        "Biloli",
        "Dharmabad",
        "Hadgaon",
        "Himayatnagar",
        "Kandhar",
        "Mahur",
        "Mudkhed",
        "Naigaon",
        "Umri"
      ],
      "Mahur": [
        "Mahur",
        "Nanded",
        "Deglur",
        "Kinwat",
        "Mukhed",
        "Ardhapur",
        "Bhokar",
        "Biloli",
        "Dharmabad",
        "Hadgaon",
        "Himayatnagar",
        "Kandhar",
        "Loha",
        "Mudkhed",
        "Naigaon",
        "Umri"
      ],
      "Mudkhed": [
        "Mudkhed",
        "Nanded",
        "Deglur",
        "Kinwat",
        "Mukhed",
        "Ardhapur",
        "Bhokar",
        "Biloli",
        "Dharmabad",
        "Hadgaon",
        "Himayatnagar",
        "Kandhar",
        "Loha",
        "Mahur",
        "Naigaon",
        "Umri"
      ],
      "Mukhed": [
        "Mukhed",
        "Nanded",
        "Deglur",
        "Kinwat",
        "Ardhapur",
        "Bhokar",
        "Biloli",
        "Dharmabad",
        "Hadgaon",
        "Himayatnagar",
        "Kandhar",
        "Loha",
        "Mahur",
        "Mudkhed",
        "Naigaon",
        "Umri"
      ],
      "Naigaon": [
        "Naigaon",
        "Nanded",
        "Deglur",
        "Kinwat",
        "Mukhed",
        "Ardhapur",
        "Bhokar",
        "Biloli",
        "Dharmabad",
        "Hadgaon",
        "Himayatnagar",
        "Kandhar",
        "Loha",
        "Mahur",
        "Mudkhed",
        "Umri"
      ],
      "Nanded": [
        "Nanded",
        "Deglur",
        "Kinwat",
        "Mukhed",
        "Ardhapur",
        "Bhokar",
        "Biloli",
        "Dharmabad",
        "Hadgaon",
        "Himayatnagar",
        "Kandhar",
        "Loha",
        "Mahur",
        "Mudkhed",
        "Naigaon",
        "Umri"
      ],
      "Umri": [
        "Umri",
        "Nanded",
        "Deglur",
        "Kinwat",
        "Mukhed",
        "Ardhapur",
        "Bhokar",
        "Biloli",
        "Dharmabad",
        "Hadgaon",
        "Himayatnagar",
        "Kandhar",
        "Loha",
        "Mahur",
        "Mudkhed",
        "Naigaon"
      ]
    },
    "Nandurbar": {
      "Akkalkuwa": [
        "Akkalkuwa",
        "Nandurbar",
        "Shahada",
        "Navapur",
        "Akrani",
        "Taloda"
      ],
      "Akrani": [
        "Akrani",
        "Nandurbar",
        "Shahada",
        "Navapur",
        "Akkalkuwa",
        "Taloda"
      ],
      "Nandurbar": [
        "Nandurbar",
        "Shahada",
        "Navapur",
        "Akkalkuwa",
        "Akrani",
        "Taloda"
      ],
      "Navapur": [
        "Navapur",
        "Nandurbar",
        "Shahada",
        "Akkalkuwa",
        "Akrani",
        "Taloda"
      ],
      "Shahada": [
        "Shahada",
        "Nandurbar",
        "Navapur",
        "Akkalkuwa",
        "Akrani",
        "Taloda"
      ],
      "Taloda": [
        "Taloda",
        "Nandurbar",
        "Shahada",
        "Navapur",
        "Akkalkuwa",
        "Akrani"
      ]
    },
    "Nashik": {
      "Baglan": [
        "Baglan",
        "Nashik",
        "Malegaon",
        "Sinnar",
        "Manmad",
        "Yevla",
        "Chandwad",
        "Deola",
        "Dindori",
        "Igatpuri",
        "Kalwan",
        "Nandgaon",
        "Niphad",
        "Peint",
        "Surgana",
        "Trimbakeshwar"
      ],
      "Chandwad": [
        "Chandwad",
        "Nashik",
        "Malegaon",
        "Sinnar",
        "Manmad",
        "Yevla",
        "Baglan",
        "Deola",
        "Dindori",
        "Igatpuri",
        "Kalwan",
        "Nandgaon",
        "Niphad",
        "Peint",
        "Surgana",
        "Trimbakeshwar"
      ],
      "Deola": [
        "Deola",
        "Nashik",
        "Malegaon",
        "Sinnar",
        "Manmad",
        "Yevla",
        "Baglan",
        "Chandwad",
        "Dindori",
        "Igatpuri",
        "Kalwan",
        "Nandgaon",
        "Niphad",
        "Peint",
        "Surgana",
        "Trimbakeshwar"
      ],
      "Dindori": [
        "Dindori",
        "Nashik",
        "Malegaon",
        "Sinnar",
        "Manmad",
        "Yevla",
        "Baglan",
        "Chandwad",
        "Deola",
        "Igatpuri",
        "Kalwan",
        "Nandgaon",
        "Niphad",
        "Peint",
        "Surgana",
        "Trimbakeshwar"
      ],
      "Igatpuri": [
        "Igatpuri",
        "Nashik",
        "Malegaon",
        "Sinnar",
        "Manmad",
        "Yevla",
        "Baglan",
        "Chandwad",
        "Deola",
        "Dindori",
        "Kalwan",
        "Nandgaon",
        "Niphad",
        "Peint",
        "Surgana",
        "Trimbakeshwar"
      ],
      "Kalwan": [
        "Kalwan",
        "Nashik",
        "Malegaon",
        "Sinnar",
        "Manmad",
        "Yevla",
        "Baglan",
        "Chandwad",
        "Deola",
        "Dindori",
        "Igatpuri",
        "Nandgaon",
        "Niphad",
        "Peint",
        "Surgana",
        "Trimbakeshwar"
      ],
      "Malegaon": [
        "Malegaon",
        "Nashik",
        "Sinnar",
        "Manmad",
        "Yevla",
        "Baglan",
        "Chandwad",
        "Deola",
        "Dindori",
        "Igatpuri",
        "Kalwan",
        "Nandgaon",
        "Niphad",
        "Peint",
        "Surgana",
        "Trimbakeshwar"
      ],
      "Nandgaon": [
        "Nandgaon",
        "Nashik",
        "Malegaon",
        "Sinnar",
        "Manmad",
        "Yevla",
        "Baglan",
        "Chandwad",
        "Deola",
        "Dindori",
        "Igatpuri",
        "Kalwan",
        "Niphad",
        "Peint",
        "Surgana",
        "Trimbakeshwar"
      ],
      "Nashik": [
        "Nashik",
        "Malegaon",
        "Sinnar",
        "Manmad",
        "Yevla",
        "Baglan",
        "Chandwad",
        "Deola",
        "Dindori",
        "Igatpuri",
        "Kalwan",
        "Nandgaon",
        "Niphad",
        "Peint",
        "Surgana",
        "Trimbakeshwar"
      ],
      "Niphad": [
        "Niphad",
        "Nashik",
        "Malegaon",
        "Sinnar",
        "Manmad",
        "Yevla",
        "Baglan",
        "Chandwad",
        "Deola",
        "Dindori",
        "Igatpuri",
        "Kalwan",
        "Nandgaon",
        "Peint",
        "Surgana",
        "Trimbakeshwar"
      ],
      "Peint": [
        "Peint",
        "Nashik",
        "Malegaon",
        "Sinnar",
        "Manmad",
        "Yevla",
        "Baglan",
        "Chandwad",
        "Deola",
        "Dindori",
        "Igatpuri",
        "Kalwan",
        "Nandgaon",
        "Niphad",
        "Surgana",
        "Trimbakeshwar"
      ],
      "Sinnar": [
        "Sinnar",
        "Nashik",
        "Malegaon",
        "Manmad",
        "Yevla",
        "Baglan",
        "Chandwad",
        "Deola",
        "Dindori",
        "Igatpuri",
        "Kalwan",
        "Nandgaon",
        "Niphad",
        "Peint",
        "Surgana",
        "Trimbakeshwar"
      ],
      "Surgana": [
        "Surgana",
        "Nashik",
        "Malegaon",
        "Sinnar",
        "Manmad",
        "Yevla",
        "Baglan",
        "Chandwad",
        "Deola",
        "Dindori",
        "Igatpuri",
        "Kalwan",
        "Nandgaon",
        "Niphad",
        "Peint",
        "Trimbakeshwar"
      ],
      "Trimbakeshwar": [
        "Trimbakeshwar",
        "Nashik",
        "Malegaon",
        "Sinnar",
        "Manmad",
        "Yevla",
        "Baglan",
        "Chandwad",
        "Deola",
        "Dindori",
        "Igatpuri",
        "Kalwan",
        "Nandgaon",
        "Niphad",
        "Peint",
        "Surgana"
      ],
      "Yevla": [
        "Yevla",
        "Nashik",
        "Malegaon",
        "Sinnar",
        "Manmad",
        "Baglan",
        "Chandwad",
        "Deola",
        "Dindori",
        "Igatpuri",
        "Kalwan",
        "Nandgaon",
        "Niphad",
        "Peint",
        "Surgana",
        "Trimbakeshwar"
      ],
      "Yeola": [
        "Yeola",
        "Dongergaon",
        "Andarsul"
      ]
    },
    "Palghar": {
      "Dahanu": [
        "Dahanu",
        "Palghar",
        "Vasai",
        "Virar",
        "Boisar",
        "Jawhar",
        "Mokhada",
        "Talasari",
        "Vikramgad",
        "Wada"
      ],
      "Jawhar": [
        "Jawhar",
        "Palghar",
        "Vasai",
        "Virar",
        "Boisar",
        "Dahanu",
        "Mokhada",
        "Talasari",
        "Vikramgad",
        "Wada"
      ],
      "Mokhada": [
        "Mokhada",
        "Palghar",
        "Vasai",
        "Virar",
        "Boisar",
        "Dahanu",
        "Jawhar",
        "Talasari",
        "Vikramgad",
        "Wada"
      ],
      "Palghar": [
        "Palghar",
        "Vasai",
        "Virar",
        "Boisar",
        "Dahanu",
        "Jawhar",
        "Mokhada",
        "Talasari",
        "Vikramgad",
        "Wada"
      ],
      "Talasari": [
        "Talasari",
        "Palghar",
        "Vasai",
        "Virar",
        "Boisar",
        "Dahanu",
        "Jawhar",
        "Mokhada",
        "Vikramgad",
        "Wada"
      ],
      "Vasai": [
        "Vasai",
        "Palghar",
        "Virar",
        "Boisar",
        "Dahanu",
        "Jawhar",
        "Mokhada",
        "Talasari",
        "Vikramgad",
        "Wada"
      ],
      "Vikramgad": [
        "Vikramgad",
        "Palghar",
        "Vasai",
        "Virar",
        "Boisar",
        "Dahanu",
        "Jawhar",
        "Mokhada",
        "Talasari",
        "Wada"
      ],
      "Wada": [
        "Wada",
        "Palghar",
        "Vasai",
        "Virar",
        "Boisar",
        "Dahanu",
        "Jawhar",
        "Mokhada",
        "Talasari",
        "Vikramgad"
      ]
    },
    "Parbhani": {
      "Gangakhed": [
        "Gangakhed",
        "Parbhani",
        "Jintur",
        "Manwath",
        "Palam",
        "Pathri",
        "Purna",
        "Sailu",
        "Sonpeth"
      ],
      "Jintur": [
        "Jintur",
        "Parbhani",
        "Gangakhed",
        "Manwath",
        "Palam",
        "Pathri",
        "Purna",
        "Sailu",
        "Sonpeth"
      ],
      "Manwath": [
        "Manwath",
        "Parbhani",
        "Gangakhed",
        "Jintur",
        "Palam",
        "Pathri",
        "Purna",
        "Sailu",
        "Sonpeth"
      ],
      "Palam": [
        "Palam",
        "Parbhani",
        "Gangakhed",
        "Jintur",
        "Manwath",
        "Pathri",
        "Purna",
        "Sailu",
        "Sonpeth"
      ],
      "Parbhani": [
        "Parbhani",
        "Gangakhed",
        "Jintur",
        "Manwath",
        "Palam",
        "Pathri",
        "Purna",
        "Sailu",
        "Sonpeth"
      ],
      "Pathri": [
        "Pathri",
        "Parbhani",
        "Gangakhed",
        "Jintur",
        "Manwath",
        "Palam",
        "Purna",
        "Sailu",
        "Sonpeth"
      ],
      "Purna": [
        "Purna",
        "Parbhani",
        "Gangakhed",
        "Jintur",
        "Manwath",
        "Palam",
        "Pathri",
        "Sailu",
        "Sonpeth"
      ],
      "Sailu": [
        "Sailu",
        "Parbhani",
        "Gangakhed",
        "Jintur",
        "Manwath",
        "Palam",
        "Pathri",
        "Purna",
        "Sonpeth"
      ],
      "Sonpeth": [
        "Sonpeth",
        "Parbhani",
        "Gangakhed",
        "Jintur",
        "Manwath",
        "Palam",
        "Pathri",
        "Purna",
        "Sailu"
      ]
    },
    "Pune": {
      "Ambegaon": [
        "Ambegaon",
        "Pune",
        "Pimpri Chinchwad",
        "Baramati",
        "Talegaon Dabhade",
        "Lonavala",
        "Bhor",
        "Chakan",
        "Daund",
        "Haveli",
        "Indapur",
        "Junnar",
        "Khed",
        "Maval",
        "Mulshi",
        "Purandar",
        "Rajgurunagar",
        "Shirur",
        "Saswad",
        "Velhe",
        "Pune City"
      ],
      "Baramati": [
        "Baramati",
        "Pune",
        "Pimpri Chinchwad",
        "Talegaon Dabhade",
        "Lonavala",
        "Ambegaon",
        "Bhor",
        "Chakan",
        "Daund",
        "Haveli",
        "Indapur",
        "Junnar",
        "Khed",
        "Maval",
        "Mulshi",
        "Purandar",
        "Rajgurunagar",
        "Shirur",
        "Saswad",
        "Velhe",
        "Pune City"
      ],
      "Bhor": [
        "Bhor",
        "Pune",
        "Pimpri Chinchwad",
        "Baramati",
        "Talegaon Dabhade",
        "Lonavala",
        "Ambegaon",
        "Chakan",
        "Daund",
        "Haveli",
        "Indapur",
        "Junnar",
        "Khed",
        "Maval",
        "Mulshi",
        "Purandar",
        "Rajgurunagar",
        "Shirur",
        "Saswad",
        "Velhe",
        "Pune City"
      ],
      "Daund": [
        "Daund",
        "Pune",
        "Pimpri Chinchwad",
        "Baramati",
        "Talegaon Dabhade",
        "Lonavala",
        "Ambegaon",
        "Bhor",
        "Chakan",
        "Haveli",
        "Indapur",
        "Junnar",
        "Khed",
        "Maval",
        "Mulshi",
        "Purandar",
        "Rajgurunagar",
        "Shirur",
        "Saswad",
        "Velhe",
        "Pune City"
      ],
      "Haveli": [
        "Haveli",
        "Pune",
        "Pimpri Chinchwad",
        "Baramati",
        "Talegaon Dabhade",
        "Lonavala",
        "Ambegaon",
        "Bhor",
        "Chakan",
        "Daund",
        "Indapur",
        "Junnar",
        "Khed",
        "Maval",
        "Mulshi",
        "Purandar",
        "Rajgurunagar",
        "Shirur",
        "Saswad",
        "Velhe",
        "Pune City"
      ],
      "Indapur": [
        "Indapur",
        "Pune",
        "Pimpri Chinchwad",
        "Baramati",
        "Talegaon Dabhade",
        "Lonavala",
        "Ambegaon",
        "Bhor",
        "Chakan",
        "Daund",
        "Haveli",
        "Junnar",
        "Khed",
        "Maval",
        "Mulshi",
        "Purandar",
        "Rajgurunagar",
        "Shirur",
        "Saswad",
        "Velhe",
        "Pune City"
      ],
      "Junnar": [
        "Junnar",
        "Pune",
        "Pimpri Chinchwad",
        "Baramati",
        "Talegaon Dabhade",
        "Lonavala",
        "Ambegaon",
        "Bhor",
        "Chakan",
        "Daund",
        "Haveli",
        "Indapur",
        "Khed",
        "Maval",
        "Mulshi",
        "Purandar",
        "Rajgurunagar",
        "Shirur",
        "Saswad",
        "Velhe",
        "Pune City"
      ],
      "Khed": [
        "Khed",
        "Pune",
        "Pimpri Chinchwad",
        "Baramati",
        "Talegaon Dabhade",
        "Lonavala",
        "Ambegaon",
        "Bhor",
        "Chakan",
        "Daund",
        "Haveli",
        "Indapur",
        "Junnar",
        "Maval",
        "Mulshi",
        "Purandar",
        "Rajgurunagar",
        "Shirur",
        "Saswad",
        "Velhe",
        "Pune City"
      ],
      "Maval": [
        "Maval",
        "Pune",
        "Pimpri Chinchwad",
        "Baramati",
        "Talegaon Dabhade",
        "Lonavala",
        "Ambegaon",
        "Bhor",
        "Chakan",
        "Daund",
        "Haveli",
        "Indapur",
        "Junnar",
        "Khed",
        "Mulshi",
        "Purandar",
        "Rajgurunagar",
        "Shirur",
        "Saswad",
        "Velhe",
        "Pune City"
      ],
      "Mulshi": [
        "Mulshi",
        "Pune",
        "Pimpri Chinchwad",
        "Baramati",
        "Talegaon Dabhade",
        "Lonavala",
        "Ambegaon",
        "Bhor",
        "Chakan",
        "Daund",
        "Haveli",
        "Indapur",
        "Junnar",
        "Khed",
        "Maval",
        "Purandar",
        "Rajgurunagar",
        "Shirur",
        "Saswad",
        "Velhe",
        "Pune City"
      ],
      "Pune City": [
        "Pune City",
        "Pune",
        "Pimpri Chinchwad",
        "Baramati",
        "Talegaon Dabhade",
        "Lonavala",
        "Ambegaon",
        "Bhor",
        "Chakan",
        "Daund",
        "Haveli",
        "Indapur",
        "Junnar",
        "Khed",
        "Maval",
        "Mulshi",
        "Purandar",
        "Rajgurunagar",
        "Shirur",
        "Saswad",
        "Velhe"
      ],
      "Purandar": [
        "Purandar",
        "Pune",
        "Pimpri Chinchwad",
        "Baramati",
        "Talegaon Dabhade",
        "Lonavala",
        "Ambegaon",
        "Bhor",
        "Chakan",
        "Daund",
        "Haveli",
        "Indapur",
        "Junnar",
        "Khed",
        "Maval",
        "Mulshi",
        "Rajgurunagar",
        "Shirur",
        "Saswad",
        "Velhe",
        "Pune City"
      ],
      "Shirur": [
        "Shirur",
        "Pune",
        "Pimpri Chinchwad",
        "Baramati",
        "Talegaon Dabhade",
        "Lonavala",
        "Ambegaon",
        "Bhor",
        "Chakan",
        "Daund",
        "Haveli",
        "Indapur",
        "Junnar",
        "Khed",
        "Maval",
        "Mulshi",
        "Purandar",
        "Rajgurunagar",
        "Saswad",
        "Velhe",
        "Pune City"
      ],
      "Velhe": [
        "Velhe",
        "Pune",
        "Pimpri Chinchwad",
        "Baramati",
        "Talegaon Dabhade",
        "Lonavala",
        "Ambegaon",
        "Bhor",
        "Chakan",
        "Daund",
        "Haveli",
        "Indapur",
        "Junnar",
        "Khed",
        "Maval",
        "Mulshi",
        "Purandar",
        "Rajgurunagar",
        "Shirur",
        "Saswad",
        "Pune City"
      ]
    },
    "Raigad": {
      "Alibag": [
        "Alibag",
        "Panvel",
        "Uran",
        "Karjat",
        "Khopoli",
        "Pen",
        "Khalapur",
        "Mahad",
        "Mangaon",
        "Mhasla",
        "Murud",
        "Poladpur",
        "Roha",
        "Shrivardhan",
        "Sudhagad",
        "Tala"
      ],
      "Karjat": [
        "Karjat",
        "Panvel",
        "Alibag",
        "Uran",
        "Khopoli",
        "Pen",
        "Khalapur",
        "Mahad",
        "Mangaon",
        "Mhasla",
        "Murud",
        "Poladpur",
        "Roha",
        "Shrivardhan",
        "Sudhagad",
        "Tala"
      ],
      "Khalapur": [
        "Khalapur",
        "Panvel",
        "Alibag",
        "Uran",
        "Karjat",
        "Khopoli",
        "Pen",
        "Mahad",
        "Mangaon",
        "Mhasla",
        "Murud",
        "Poladpur",
        "Roha",
        "Shrivardhan",
        "Sudhagad",
        "Tala"
      ],
      "Mahad": [
        "Mahad",
        "Panvel",
        "Alibag",
        "Uran",
        "Karjat",
        "Khopoli",
        "Pen",
        "Khalapur",
        "Mangaon",
        "Mhasla",
        "Murud",
        "Poladpur",
        "Roha",
        "Shrivardhan",
        "Sudhagad",
        "Tala"
      ],
      "Mangaon": [
        "Mangaon",
        "Panvel",
        "Alibag",
        "Uran",
        "Karjat",
        "Khopoli",
        "Pen",
        "Khalapur",
        "Mahad",
        "Mhasla",
        "Murud",
        "Poladpur",
        "Roha",
        "Shrivardhan",
        "Sudhagad",
        "Tala"
      ],
      "Mhasla": [
        "Mhasla",
        "Panvel",
        "Alibag",
        "Uran",
        "Karjat",
        "Khopoli",
        "Pen",
        "Khalapur",
        "Mahad",
        "Mangaon",
        "Murud",
        "Poladpur",
        "Roha",
        "Shrivardhan",
        "Sudhagad",
        "Tala"
      ],
      "Murud": [
        "Murud",
        "Panvel",
        "Alibag",
        "Uran",
        "Karjat",
        "Khopoli",
        "Pen",
        "Khalapur",
        "Mahad",
        "Mangaon",
        "Mhasla",
        "Poladpur",
        "Roha",
        "Shrivardhan",
        "Sudhagad",
        "Tala"
      ],
      "Panvel": [
        "Panvel",
        "Alibag",
        "Uran",
        "Karjat",
        "Khopoli",
        "Pen",
        "Khalapur",
        "Mahad",
        "Mangaon",
        "Mhasla",
        "Murud",
        "Poladpur",
        "Roha",
        "Shrivardhan",
        "Sudhagad",
        "Tala"
      ],
      "Pen": [
        "Pen",
        "Panvel",
        "Alibag",
        "Uran",
        "Karjat",
        "Khopoli",
        "Khalapur",
        "Mahad",
        "Mangaon",
        "Mhasla",
        "Murud",
        "Poladpur",
        "Roha",
        "Shrivardhan",
        "Sudhagad",
        "Tala"
      ],
      "Poladpur": [
        "Poladpur",
        "Panvel",
        "Alibag",
        "Uran",
        "Karjat",
        "Khopoli",
        "Pen",
        "Khalapur",
        "Mahad",
        "Mangaon",
        "Mhasla",
        "Murud",
        "Roha",
        "Shrivardhan",
        "Sudhagad",
        "Tala"
      ],
      "Roha": [
        "Roha",
        "Panvel",
        "Alibag",
        "Uran",
        "Karjat",
        "Khopoli",
        "Pen",
        "Khalapur",
        "Mahad",
        "Mangaon",
        "Mhasla",
        "Murud",
        "Poladpur",
        "Shrivardhan",
        "Sudhagad",
        "Tala"
      ],
      "Shrivardhan": [
        "Shrivardhan",
        "Panvel",
        "Alibag",
        "Uran",
        "Karjat",
        "Khopoli",
        "Pen",
        "Khalapur",
        "Mahad",
        "Mangaon",
        "Mhasla",
        "Murud",
        "Poladpur",
        "Roha",
        "Sudhagad",
        "Tala"
      ],
      "Sudhagad": [
        "Sudhagad",
        "Panvel",
        "Alibag",
        "Uran",
        "Karjat",
        "Khopoli",
        "Pen",
        "Khalapur",
        "Mahad",
        "Mangaon",
        "Mhasla",
        "Murud",
        "Poladpur",
        "Roha",
        "Shrivardhan",
        "Tala"
      ],
      "Tala": [
        "Tala",
        "Panvel",
        "Alibag",
        "Uran",
        "Karjat",
        "Khopoli",
        "Pen",
        "Khalapur",
        "Mahad",
        "Mangaon",
        "Mhasla",
        "Murud",
        "Poladpur",
        "Roha",
        "Shrivardhan",
        "Sudhagad"
      ],
      "Uran": [
        "Uran",
        "Panvel",
        "Alibag",
        "Karjat",
        "Khopoli",
        "Pen",
        "Khalapur",
        "Mahad",
        "Mangaon",
        "Mhasla",
        "Murud",
        "Poladpur",
        "Roha",
        "Shrivardhan",
        "Sudhagad",
        "Tala"
      ]
    },
    "Ratnagiri": {
      "Chiplun": [
        "Chiplun",
        "Ratnagiri",
        "Khed",
        "Dapoli",
        "Guhagar",
        "Lanja",
        "Mandangad",
        "Rajapur",
        "Sangameshwar"
      ],
      "Dapoli": [
        "Dapoli",
        "Ratnagiri",
        "Chiplun",
        "Khed",
        "Guhagar",
        "Lanja",
        "Mandangad",
        "Rajapur",
        "Sangameshwar"
      ],
      "Guhagar": [
        "Guhagar",
        "Ratnagiri",
        "Chiplun",
        "Khed",
        "Dapoli",
        "Lanja",
        "Mandangad",
        "Rajapur",
        "Sangameshwar"
      ],
      "Khed": [
        "Khed",
        "Ratnagiri",
        "Chiplun",
        "Dapoli",
        "Guhagar",
        "Lanja",
        "Mandangad",
        "Rajapur",
        "Sangameshwar"
      ],
      "Lanja": [
        "Lanja",
        "Ratnagiri",
        "Chiplun",
        "Khed",
        "Dapoli",
        "Guhagar",
        "Mandangad",
        "Rajapur",
        "Sangameshwar"
      ],
      "Mandangad": [
        "Mandangad",
        "Ratnagiri",
        "Chiplun",
        "Khed",
        "Dapoli",
        "Guhagar",
        "Lanja",
        "Rajapur",
        "Sangameshwar"
      ],
      "Rajapur": [
        "Rajapur",
        "Ratnagiri",
        "Chiplun",
        "Khed",
        "Dapoli",
        "Guhagar",
        "Lanja",
        "Mandangad",
        "Sangameshwar"
      ],
      "Ratnagiri": [
        "Ratnagiri",
        "Chiplun",
        "Khed",
        "Dapoli",
        "Guhagar",
        "Lanja",
        "Mandangad",
        "Rajapur",
        "Sangameshwar"
      ],
      "Sangameshwar": [
        "Sangameshwar",
        "Ratnagiri",
        "Chiplun",
        "Khed",
        "Dapoli",
        "Guhagar",
        "Lanja",
        "Mandangad",
        "Rajapur"
      ]
    },
    "Sangli": {
      "Atpadi": [
        "Atpadi",
        "Sangli",
        "Miraj",
        "Islampur",
        "Vita",
        "Tasgaon",
        "Jat",
        "Kadegaon",
        "Kavathe Mahankal",
        "Khanapur",
        "Palus",
        "Shirala",
        "Walwa"
      ],
      "Jat": [
        "Jat",
        "Sangli",
        "Miraj",
        "Islampur",
        "Vita",
        "Tasgaon",
        "Atpadi",
        "Kadegaon",
        "Kavathe Mahankal",
        "Khanapur",
        "Palus",
        "Shirala",
        "Walwa"
      ],
      "Kadegaon": [
        "Kadegaon",
        "Sangli",
        "Miraj",
        "Islampur",
        "Vita",
        "Tasgaon",
        "Atpadi",
        "Jat",
        "Kavathe Mahankal",
        "Khanapur",
        "Palus",
        "Shirala",
        "Walwa"
      ],
      "Kavathe Mahankal": [
        "Kavathe Mahankal",
        "Sangli",
        "Miraj",
        "Islampur",
        "Vita",
        "Tasgaon",
        "Atpadi",
        "Jat",
        "Kadegaon",
        "Khanapur",
        "Palus",
        "Shirala",
        "Walwa"
      ],
      "Khanapur": [
        "Khanapur",
        "Sangli",
        "Miraj",
        "Islampur",
        "Vita",
        "Tasgaon",
        "Atpadi",
        "Jat",
        "Kadegaon",
        "Kavathe Mahankal",
        "Palus",
        "Shirala",
        "Walwa"
      ],
      "Miraj": [
        "Miraj",
        "Sangli",
        "Islampur",
        "Vita",
        "Tasgaon",
        "Atpadi",
        "Jat",
        "Kadegaon",
        "Kavathe Mahankal",
        "Khanapur",
        "Palus",
        "Shirala",
        "Walwa"
      ],
      "Palus": [
        "Palus",
        "Sangli",
        "Miraj",
        "Islampur",
        "Vita",
        "Tasgaon",
        "Atpadi",
        "Jat",
        "Kadegaon",
        "Kavathe Mahankal",
        "Khanapur",
        "Shirala",
        "Walwa"
      ],
      "Shirala": [
        "Shirala",
        "Sangli",
        "Miraj",
        "Islampur",
        "Vita",
        "Tasgaon",
        "Atpadi",
        "Jat",
        "Kadegaon",
        "Kavathe Mahankal",
        "Khanapur",
        "Palus",
        "Walwa"
      ],
      "Tasgaon": [
        "Tasgaon",
        "Sangli",
        "Miraj",
        "Islampur",
        "Vita",
        "Atpadi",
        "Jat",
        "Kadegaon",
        "Kavathe Mahankal",
        "Khanapur",
        "Palus",
        "Shirala",
        "Walwa"
      ],
      "Walwa": [
        "Walwa",
        "Sangli",
        "Miraj",
        "Islampur",
        "Vita",
        "Tasgaon",
        "Atpadi",
        "Jat",
        "Kadegaon",
        "Kavathe Mahankal",
        "Khanapur",
        "Palus",
        "Shirala"
      ]
    },
    "Satara": {
      "Jaoli": [
        "Jaoli",
        "Satara",
        "Karad",
        "Phaltan",
        "Wai",
        "Mahabaleshwar",
        "Dahiwadi",
        "Khandala",
        "Khatav",
        "Koregaon",
        "Patan",
        "Vaduj",
        "Man"
      ],
      "Karad": [
        "Karad",
        "Satara",
        "Phaltan",
        "Wai",
        "Mahabaleshwar",
        "Dahiwadi",
        "Jaoli",
        "Khandala",
        "Khatav",
        "Koregaon",
        "Patan",
        "Vaduj",
        "Man"
      ],
      "Khandala": [
        "Khandala",
        "Satara",
        "Karad",
        "Phaltan",
        "Wai",
        "Mahabaleshwar",
        "Dahiwadi",
        "Jaoli",
        "Khatav",
        "Koregaon",
        "Patan",
        "Vaduj",
        "Man"
      ],
      "Khatav": [
        "Khatav",
        "Satara",
        "Karad",
        "Phaltan",
        "Wai",
        "Mahabaleshwar",
        "Dahiwadi",
        "Jaoli",
        "Khandala",
        "Koregaon",
        "Patan",
        "Vaduj",
        "Man"
      ],
      "Koregaon": [
        "Koregaon",
        "Satara",
        "Karad",
        "Phaltan",
        "Wai",
        "Mahabaleshwar",
        "Dahiwadi",
        "Jaoli",
        "Khandala",
        "Khatav",
        "Patan",
        "Vaduj",
        "Man"
      ],
      "Mahabaleshwar": [
        "Mahabaleshwar",
        "Satara",
        "Karad",
        "Phaltan",
        "Wai",
        "Dahiwadi",
        "Jaoli",
        "Khandala",
        "Khatav",
        "Koregaon",
        "Patan",
        "Vaduj",
        "Man"
      ],
      "Man": [
        "Man",
        "Satara",
        "Karad",
        "Phaltan",
        "Wai",
        "Mahabaleshwar",
        "Dahiwadi",
        "Jaoli",
        "Khandala",
        "Khatav",
        "Koregaon",
        "Patan",
        "Vaduj"
      ],
      "Patan": [
        "Patan",
        "Satara",
        "Karad",
        "Phaltan",
        "Wai",
        "Mahabaleshwar",
        "Dahiwadi",
        "Jaoli",
        "Khandala",
        "Khatav",
        "Koregaon",
        "Vaduj",
        "Man"
      ],
      "Phaltan": [
        "Phaltan",
        "Satara",
        "Karad",
        "Wai",
        "Mahabaleshwar",
        "Dahiwadi",
        "Jaoli",
        "Khandala",
        "Khatav",
        "Koregaon",
        "Patan",
        "Vaduj",
        "Man"
      ],
      "Satara": [
        "Satara",
        "Karad",
        "Phaltan",
        "Wai",
        "Mahabaleshwar",
        "Dahiwadi",
        "Jaoli",
        "Khandala",
        "Khatav",
        "Koregaon",
        "Patan",
        "Vaduj",
        "Man"
      ],
      "Wai": [
        "Wai",
        "Satara",
        "Karad",
        "Phaltan",
        "Mahabaleshwar",
        "Dahiwadi",
        "Jaoli",
        "Khandala",
        "Khatav",
        "Koregaon",
        "Patan",
        "Vaduj",
        "Man"
      ]
    },
    "Sindhudurg": {
      "Devgad": [
        "Devgad",
        "Kankavli",
        "Sawantwadi",
        "Malvan",
        "Kudal",
        "Dodamarg",
        "Oros",
        "Vaibhavwadi",
        "Vengurla"
      ],
      "Dodamarg": [
        "Dodamarg",
        "Kankavli",
        "Sawantwadi",
        "Malvan",
        "Kudal",
        "Devgad",
        "Oros",
        "Vaibhavwadi",
        "Vengurla"
      ],
      "Kankavli": [
        "Kankavli",
        "Sawantwadi",
        "Malvan",
        "Kudal",
        "Devgad",
        "Dodamarg",
        "Oros",
        "Vaibhavwadi",
        "Vengurla"
      ],
      "Kudal": [
        "Kudal",
        "Kankavli",
        "Sawantwadi",
        "Malvan",
        "Devgad",
        "Dodamarg",
        "Oros",
        "Vaibhavwadi",
        "Vengurla"
      ],
      "Malvan": [
        "Malvan",
        "Kankavli",
        "Sawantwadi",
        "Kudal",
        "Devgad",
        "Dodamarg",
        "Oros",
        "Vaibhavwadi",
        "Vengurla"
      ],
      "Sawantwadi": [
        "Sawantwadi",
        "Kankavli",
        "Malvan",
        "Kudal",
        "Devgad",
        "Dodamarg",
        "Oros",
        "Vaibhavwadi",
        "Vengurla"
      ],
      "Vaibhavwadi": [
        "Vaibhavwadi",
        "Kankavli",
        "Sawantwadi",
        "Malvan",
        "Kudal",
        "Devgad",
        "Dodamarg",
        "Oros",
        "Vengurla"
      ],
      "Vengurla": [
        "Vengurla",
        "Kankavli",
        "Sawantwadi",
        "Malvan",
        "Kudal",
        "Devgad",
        "Dodamarg",
        "Oros",
        "Vaibhavwadi"
      ]
    },
    "Solapur": {
      "Akkalkot": [
        "Akkalkot",
        "Solapur",
        "Pandharpur",
        "Barshi",
        "Akluj",
        "Karmala",
        "Madha",
        "Malshiras",
        "Mangalvedhe",
        "Mohol",
        "Sangole",
        "Solapur North",
        "Solapur South"
      ],
      "Barshi": [
        "Barshi",
        "Solapur",
        "Pandharpur",
        "Akkalkot",
        "Akluj",
        "Karmala",
        "Madha",
        "Malshiras",
        "Mangalvedhe",
        "Mohol",
        "Sangole",
        "Solapur North",
        "Solapur South"
      ],
      "Karmala": [
        "Karmala",
        "Solapur",
        "Pandharpur",
        "Barshi",
        "Akkalkot",
        "Akluj",
        "Madha",
        "Malshiras",
        "Mangalvedhe",
        "Mohol",
        "Sangole",
        "Solapur North",
        "Solapur South"
      ],
      "Madha": [
        "Madha",
        "Solapur",
        "Pandharpur",
        "Barshi",
        "Akkalkot",
        "Akluj",
        "Karmala",
        "Malshiras",
        "Mangalvedhe",
        "Mohol",
        "Sangole",
        "Solapur North",
        "Solapur South"
      ],
      "Malshiras": [
        "Malshiras",
        "Solapur",
        "Pandharpur",
        "Barshi",
        "Akkalkot",
        "Akluj",
        "Karmala",
        "Madha",
        "Mangalvedhe",
        "Mohol",
        "Sangole",
        "Solapur North",
        "Solapur South"
      ],
      "Mangalvedhe": [
        "Mangalvedhe",
        "Solapur",
        "Pandharpur",
        "Barshi",
        "Akkalkot",
        "Akluj",
        "Karmala",
        "Madha",
        "Malshiras",
        "Mohol",
        "Sangole",
        "Solapur North",
        "Solapur South"
      ],
      "Mohol": [
        "Mohol",
        "Solapur",
        "Pandharpur",
        "Barshi",
        "Akkalkot",
        "Akluj",
        "Karmala",
        "Madha",
        "Malshiras",
        "Mangalvedhe",
        "Sangole",
        "Solapur North",
        "Solapur South"
      ],
      "Pandharpur": [
        "Pandharpur",
        "Solapur",
        "Barshi",
        "Akkalkot",
        "Akluj",
        "Karmala",
        "Madha",
        "Malshiras",
        "Mangalvedhe",
        "Mohol",
        "Sangole",
        "Solapur North",
        "Solapur South"
      ],
      "Sangole": [
        "Sangole",
        "Solapur",
        "Pandharpur",
        "Barshi",
        "Akkalkot",
        "Akluj",
        "Karmala",
        "Madha",
        "Malshiras",
        "Mangalvedhe",
        "Mohol",
        "Solapur North",
        "Solapur South"
      ],
      "Solapur North": [
        "Solapur North",
        "Solapur",
        "Pandharpur",
        "Barshi",
        "Akkalkot",
        "Akluj",
        "Karmala",
        "Madha",
        "Malshiras",
        "Mangalvedhe",
        "Mohol",
        "Sangole",
        "Solapur South"
      ],
      "Solapur South": [
        "Solapur South",
        "Solapur",
        "Pandharpur",
        "Barshi",
        "Akkalkot",
        "Akluj",
        "Karmala",
        "Madha",
        "Malshiras",
        "Mangalvedhe",
        "Mohol",
        "Sangole",
        "Solapur North"
      ]
    },
    "Thane": {
      "Ambarnath": [
        "Ambarnath",
        "Thane",
        "Kalyan",
        "Dombivli",
        "Bhiwandi",
        "Ulhasnagar",
        "Badlapur",
        "Murbad",
        "Shahapur"
      ],
      "Bhiwandi": [
        "Bhiwandi",
        "Thane",
        "Kalyan",
        "Dombivli",
        "Ulhasnagar",
        "Ambarnath",
        "Badlapur",
        "Murbad",
        "Shahapur"
      ],
      "Kalyan": [
        "Kalyan",
        "Thane",
        "Dombivli",
        "Bhiwandi",
        "Ulhasnagar",
        "Ambarnath",
        "Badlapur",
        "Murbad",
        "Shahapur"
      ],
      "Murbad": [
        "Murbad",
        "Thane",
        "Kalyan",
        "Dombivli",
        "Bhiwandi",
        "Ulhasnagar",
        "Ambarnath",
        "Badlapur",
        "Shahapur"
      ],
      "Shahapur": [
        "Shahapur",
        "Thane",
        "Kalyan",
        "Dombivli",
        "Bhiwandi",
        "Ulhasnagar",
        "Ambarnath",
        "Badlapur",
        "Murbad"
      ],
      "Thane": [
        "Thane",
        "Kalyan",
        "Dombivli",
        "Bhiwandi",
        "Ulhasnagar",
        "Ambarnath",
        "Badlapur",
        "Murbad",
        "Shahapur"
      ],
      "Ulhasnagar": [
        "Ulhasnagar",
        "Thane",
        "Kalyan",
        "Dombivli",
        "Bhiwandi",
        "Ambarnath",
        "Badlapur",
        "Murbad",
        "Shahapur"
      ]
    },
    "Wardha": {
      "Arvi": [
        "Arvi",
        "Wardha",
        "Hinganghat",
        "Ashti",
        "Deoli",
        "Karanja",
        "Samudrapur",
        "Seloo"
      ],
      "Ashti": [
        "Ashti",
        "Wardha",
        "Hinganghat",
        "Arvi",
        "Deoli",
        "Karanja",
        "Samudrapur",
        "Seloo"
      ],
      "Deoli": [
        "Deoli",
        "Wardha",
        "Hinganghat",
        "Arvi",
        "Ashti",
        "Karanja",
        "Samudrapur",
        "Seloo"
      ],
      "Hinganghat": [
        "Hinganghat",
        "Wardha",
        "Arvi",
        "Ashti",
        "Deoli",
        "Karanja",
        "Samudrapur",
        "Seloo"
      ],
      "Karanja": [
        "Karanja",
        "Wardha",
        "Hinganghat",
        "Arvi",
        "Ashti",
        "Deoli",
        "Samudrapur",
        "Seloo"
      ],
      "Samudrapur": [
        "Samudrapur",
        "Wardha",
        "Hinganghat",
        "Arvi",
        "Ashti",
        "Deoli",
        "Karanja",
        "Seloo"
      ],
      "Seloo": [
        "Seloo",
        "Wardha",
        "Hinganghat",
        "Arvi",
        "Ashti",
        "Deoli",
        "Karanja",
        "Samudrapur"
      ],
      "Wardha": [
        "Wardha",
        "Hinganghat",
        "Arvi",
        "Ashti",
        "Deoli",
        "Karanja",
        "Samudrapur",
        "Seloo"
      ]
    },
    "Washim": {
      "Karanja": [
        "Karanja",
        "Washim",
        "Risod",
        "Malegaon",
        "Mangrulpir",
        "Manora"
      ],
      "Malegaon": [
        "Malegaon",
        "Washim",
        "Karanja",
        "Risod",
        "Mangrulpir",
        "Manora"
      ],
      "Mangrulpir": [
        "Mangrulpir",
        "Washim",
        "Karanja",
        "Risod",
        "Malegaon",
        "Manora"
      ],
      "Manora": [
        "Manora",
        "Washim",
        "Karanja",
        "Risod",
        "Malegaon",
        "Mangrulpir"
      ],
      "Risod": [
        "Risod",
        "Washim",
        "Karanja",
        "Malegaon",
        "Mangrulpir",
        "Manora"
      ],
      "Washim": [
        "Washim",
        "Karanja",
        "Risod",
        "Malegaon",
        "Mangrulpir",
        "Manora"
      ]
    },
    "Yavatmal": {
      "Arni": [
        "Arni",
        "Yavatmal",
        "Pusad",
        "Wani",
        "Umarkhed",
        "Darwha",
        "Babulgaon",
        "Digras",
        "Ghatanji",
        "Kalamb",
        "Mahagaon",
        "Maregaon",
        "Ner",
        "Pandharkawada",
        "Ralegaon",
        "Zari Jamani"
      ],
      "Babulgaon": [
        "Babulgaon",
        "Yavatmal",
        "Pusad",
        "Wani",
        "Umarkhed",
        "Darwha",
        "Arni",
        "Digras",
        "Ghatanji",
        "Kalamb",
        "Mahagaon",
        "Maregaon",
        "Ner",
        "Pandharkawada",
        "Ralegaon",
        "Zari Jamani"
      ],
      "Darwha": [
        "Darwha",
        "Yavatmal",
        "Pusad",
        "Wani",
        "Umarkhed",
        "Arni",
        "Babulgaon",
        "Digras",
        "Ghatanji",
        "Kalamb",
        "Mahagaon",
        "Maregaon",
        "Ner",
        "Pandharkawada",
        "Ralegaon",
        "Zari Jamani"
      ],
      "Digras": [
        "Digras",
        "Yavatmal",
        "Pusad",
        "Wani",
        "Umarkhed",
        "Darwha",
        "Arni",
        "Babulgaon",
        "Ghatanji",
        "Kalamb",
        "Mahagaon",
        "Maregaon",
        "Ner",
        "Pandharkawada",
        "Ralegaon",
        "Zari Jamani"
      ],
      "Ghatanji": [
        "Ghatanji",
        "Yavatmal",
        "Pusad",
        "Wani",
        "Umarkhed",
        "Darwha",
        "Arni",
        "Babulgaon",
        "Digras",
        "Kalamb",
        "Mahagaon",
        "Maregaon",
        "Ner",
        "Pandharkawada",
        "Ralegaon",
        "Zari Jamani"
      ],
      "Kalamb": [
        "Kalamb",
        "Yavatmal",
        "Pusad",
        "Wani",
        "Umarkhed",
        "Darwha",
        "Arni",
        "Babulgaon",
        "Digras",
        "Ghatanji",
        "Mahagaon",
        "Maregaon",
        "Ner",
        "Pandharkawada",
        "Ralegaon",
        "Zari Jamani"
      ],
      "Mahagaon": [
        "Mahagaon",
        "Yavatmal",
        "Pusad",
        "Wani",
        "Umarkhed",
        "Darwha",
        "Arni",
        "Babulgaon",
        "Digras",
        "Ghatanji",
        "Kalamb",
        "Maregaon",
        "Ner",
        "Pandharkawada",
        "Ralegaon",
        "Zari Jamani"
      ],
      "Maregaon": [
        "Maregaon",
        "Yavatmal",
        "Pusad",
        "Wani",
        "Umarkhed",
        "Darwha",
        "Arni",
        "Babulgaon",
        "Digras",
        "Ghatanji",
        "Kalamb",
        "Mahagaon",
        "Ner",
        "Pandharkawada",
        "Ralegaon",
        "Zari Jamani"
      ],
      "Ner": [
        "Ner",
        "Yavatmal",
        "Pusad",
        "Wani",
        "Umarkhed",
        "Darwha",
        "Arni",
        "Babulgaon",
        "Digras",
        "Ghatanji",
        "Kalamb",
        "Mahagaon",
        "Maregaon",
        "Pandharkawada",
        "Ralegaon",
        "Zari Jamani"
      ],
      "Pandharkawada": [
        "Pandharkawada",
        "Yavatmal",
        "Pusad",
        "Wani",
        "Umarkhed",
        "Darwha",
        "Arni",
        "Babulgaon",
        "Digras",
        "Ghatanji",
        "Kalamb",
        "Mahagaon",
        "Maregaon",
        "Ner",
        "Ralegaon",
        "Zari Jamani"
      ],
      "Pusad": [
        "Pusad",
        "Yavatmal",
        "Wani",
        "Umarkhed",
        "Darwha",
        "Arni",
        "Babulgaon",
        "Digras",
        "Ghatanji",
        "Kalamb",
        "Mahagaon",
        "Maregaon",
        "Ner",
        "Pandharkawada",
        "Ralegaon",
        "Zari Jamani"
      ],
      "Ralegaon": [
        "Ralegaon",
        "Yavatmal",
        "Pusad",
        "Wani",
        "Umarkhed",
        "Darwha",
        "Arni",
        "Babulgaon",
        "Digras",
        "Ghatanji",
        "Kalamb",
        "Mahagaon",
        "Maregaon",
        "Ner",
        "Pandharkawada",
        "Zari Jamani"
      ],
      "Umarkhed": [
        "Umarkhed",
        "Yavatmal",
        "Pusad",
        "Wani",
        "Darwha",
        "Arni",
        "Babulgaon",
        "Digras",
        "Ghatanji",
        "Kalamb",
        "Mahagaon",
        "Maregaon",
        "Ner",
        "Pandharkawada",
        "Ralegaon",
        "Zari Jamani"
      ],
      "Wani": [
        "Wani",
        "Yavatmal",
        "Pusad",
        "Umarkhed",
        "Darwha",
        "Arni",
        "Babulgaon",
        "Digras",
        "Ghatanji",
        "Kalamb",
        "Mahagaon",
        "Maregaon",
        "Ner",
        "Pandharkawada",
        "Ralegaon",
        "Zari Jamani"
      ],
      "Yavatmal": [
        "Yavatmal",
        "Pusad",
        "Wani",
        "Umarkhed",
        "Darwha",
        "Arni",
        "Babulgaon",
        "Digras",
        "Ghatanji",
        "Kalamb",
        "Mahagaon",
        "Maregaon",
        "Ner",
        "Pandharkawada",
        "Ralegaon",
        "Zari Jamani"
      ],
      "Zari Jamani": [
        "Zari Jamani",
        "Yavatmal",
        "Pusad",
        "Wani",
        "Umarkhed",
        "Darwha",
        "Arni",
        "Babulgaon",
        "Digras",
        "Ghatanji",
        "Kalamb",
        "Mahagaon",
        "Maregaon",
        "Ner",
        "Pandharkawada",
        "Ralegaon"
      ]
    }
  },
  "Gujarat": {},
  "Karnataka": {},
  "Delhi": {},
  "Uttar Pradesh": {}
}